{"date":"2026-07-20","rows":[{"drug":"VALPROIC ACID - DEPAKINE 57.64 MG/ML IN 150 ML SYRUP -TRD","patients":2,"qty":18003.0,"mrns":["606112","702465"],"avg":9001.5,"patientRows":[{"mrn":"606112","name":"WEJDAN MOHAMMED ALI HAKAMI","speciality":"","qty":9001.5},{"mrn":"702465","name":"SALMAN HASSAN MOHAMMED ALSHARYAWI","speciality":"","qty":9001.5}]},{"drug":"SODIUM CARBOXYMETHYLCELLULOSE:GLYCERINE-OPTIVE UD-0.5%:0.9% MINIMS","patients":22,"qty":1350.0,"mrns":["104651","305746","239390","6569","38620","10748","550173","363224","289849","806081","654600","129057","25328","293298","462545","319529","49080","46179","609926","22447","665653","698512"],"avg":61.36,"patientRows":[{"mrn":"104651","name":"ALAWI ALI ALAWI ALJARRASH","speciality":"","qty":61.36},{"mrn":"305746","name":"FATIMAH ALI MOHAMMED AL YAQUB","speciality":"","qty":61.36},{"mrn":"239390","name":"ZANAAB ALI AHMED ALABAS","speciality":"","qty":61.36},{"mrn":"6569","name":"MONA ALI S ALKHURIDAH","speciality":"","qty":61.36},{"mrn":"38620","name":"MADINA ABDULAH AHMAD AL MATOOQ","speciality":"","qty":61.36},{"mrn":"10748","name":"AHMAD SAEED ABDULMOHSIN AL GHURAB","speciality":"","qty":61.36},{"mrn":"550173","name":"HUSSAIN MUSA ALI AL HASHEM","speciality":"","qty":61.36},{"mrn":"363224","name":"AHMED ABDULLAH HASSAN ALSOLEEBE","speciality":"","qty":61.36},{"mrn":"289849","name":"AFRAH MANSOUR ABDULAH ALHIRZ","speciality":"","qty":61.36},{"mrn":"806081","name":"SALMAN ABDULLAH H ALMADEH","speciality":"","qty":61.36},{"mrn":"654600","name":"ANWAR HUSSAIN A ALMULLA","speciality":"","qty":61.36},{"mrn":"129057","name":"MASOUMAH SALMAN IBRAHIM ALMARHOON","speciality":"","qty":61.36},{"mrn":"25328","name":"AFAF AHMAD SALEH AL ALI","speciality":"","qty":61.36},{"mrn":"293298","name":"ZAHRA ABDULLAH ESSA AL SALEM","speciality":"","qty":61.36},{"mrn":"462545","name":"DANA AHMAD ALI ALMARHOON","speciality":"","qty":61.36},{"mrn":"319529","name":"ZAHRA ALI RAMADAN ALFADAL","speciality":"","qty":61.36},{"mrn":"49080","name":"AFRAA MOHAMMED M ALHAJRI","speciality":"","qty":61.36},{"mrn":"46179","name":"SAEEDAH AHMED BIN MOHAMMED ALFARAG","speciality":"","qty":61.36},{"mrn":"609926","name":"NAJAH ABDULLAH HUSEN AL BORI","speciality":"","qty":61.36},{"mrn":"22447","name":"ZAHRA ABDULLAH H ALORAYEDH","speciality":"","qty":61.36},{"mrn":"665653","name":"AMIR HUSEN ALI ALMUBARAK","speciality":"","qty":61.36},{"mrn":"698512","name":"SAEED SAEED HUSSEIN SALEH","speciality":"","qty":61.36}]},{"drug":"CHOLECALCIFEROL; VITAMIN D3- VIDROP 2800 UNIT/ML ORAL DROPS -TRD","patients":6,"qty":1025.0,"mrns":["670452","826559","804155","409951","824200","812809"],"avg":170.83,"patientRows":[{"mrn":"670452","name":"SAHAB RASHAD M ALZABI","speciality":"","qty":170.83},{"mrn":"826559","name":"ILIYA SHAKER ALI ALZAHER","speciality":"","qty":170.83},{"mrn":"804155","name":"ELAF MAHER SALEH AL HAMMADI","speciality":"","qty":170.83},{"mrn":"409951","name":"RIDA FOUAD ALI ABUNAYAN","speciality":"","qty":170.83},{"mrn":"824200","name":"QAMAR MONER NURI ALSAKHIN","speciality":"","qty":170.83},{"mrn":"812809","name":"FARIS ABDULAZIZ HABUB ALSAYG","speciality":"","qty":170.83}]},{"drug":"hydrALAZINE  - APROLIN  25 MG TABLET -TRD","patients":5,"qty":800.0,"mrns":["741305","798069","4307","429955","40859"],"avg":160.0,"patientRows":[{"mrn":"741305","name":"SAEED SALMAN M AL ABDULAAL","speciality":"","qty":160.0},{"mrn":"798069","name":"ZAINAB ALI ABDALLA ALQUDAIHI","speciality":"","qty":160.0},{"mrn":"4307","name":"ZAHRA SALEH AHMED ALSALAM","speciality":"","qty":160.0},{"mrn":"429955","name":"MAHDY SALEH ABDALLA ALMADEH","speciality":"","qty":160.0},{"mrn":"40859","name":"ALI HASSAN YOSEF ALJANABI","speciality":"","qty":160.0}]},{"drug":"CELECOXIB - CELECT 200 MG CAPSULE -TRD","patients":12,"qty":690.0,"mrns":["260514","523394","111086","72454","88851","413371","109554","379634","507297","829991","462186","717215"],"avg":57.5,"patientRows":[{"mrn":"260514","name":"SADIA HABIB A ALHMAM","speciality":"","qty":57.5},{"mrn":"523394","name":"SHEJAA QAZEM AHMED HASHEM","speciality":"","qty":57.5},{"mrn":"111086","name":"KAMILAH ABDULWAHED MOHAMMED ALMAEENI","speciality":"","qty":57.5},{"mrn":"72454","name":"ZAINAB ESSA M AL ABDULWAHAB","speciality":"","qty":57.5},{"mrn":"88851","name":"MONA ABDULKAREEM M AL KHATER","speciality":"","qty":57.5},{"mrn":"413371","name":"FATMA ABDULJALEEL IBRAHIM ALMESHAMA","speciality":"","qty":57.5},{"mrn":"109554","name":"MASOOMA ALI JASEM ALHERANI","speciality":"","qty":57.5},{"mrn":"379634","name":"MOHSEN ABBAS A AL DABEL","speciality":"","qty":57.5},{"mrn":"507297","name":"BADRIYAH IBRAHIM ABDALLA MALALLAH","speciality":"","qty":57.5},{"mrn":"829991","name":"AMIRAH RASHED BIN MOHAMMED ALHAJRY","speciality":"","qty":57.5},{"mrn":"462186","name":"FATEMAH MOHAMMED A Al dawad","speciality":"","qty":57.5},{"mrn":"717215","name":"NAEMA ALI SALEH ALHAMAL","speciality":"","qty":57.5}]},{"drug":"CALCIUM CARBONATE - MAXICAL PLAIN 600 MG TABLET -TRD","patients":16,"qty":660.0,"mrns":["38605","5913","25410","41318","735217","4307","541502","46179","519197","271377","292942","646498","825827","553115","305911","237852"],"avg":41.25,"patientRows":[{"mrn":"38605","name":"HUDA AJEEB SALEH ALHASSAN","speciality":"","qty":41.25},{"mrn":"5913","name":"NAGYA ALI HUSEN ALHAKIM","speciality":"","qty":41.25},{"mrn":"25410","name":"MASOUMAH ALI Ahmed ALSUDAN","speciality":"","qty":41.25},{"mrn":"41318","name":"MASOUMAH IBRAHIM Y ALJAROODI","speciality":"","qty":41.25},{"mrn":"735217","name":"LAILA ALI BIN RADHI ALALWAN","speciality":"","qty":41.25},{"mrn":"4307","name":"ZAHRA SALEH AHMED ALSALAM","speciality":"","qty":41.25},{"mrn":"541502","name":"HANADI JAAFER SALEH ALBAHRANI","speciality":"","qty":41.25},{"mrn":"46179","name":"SAEEDAH AHMED BIN MOHAMMED ALFARAG","speciality":"","qty":41.25},{"mrn":"519197","name":"ZAINAB ALI A ALMATAR","speciality":"","qty":41.25},{"mrn":"271377","name":"HOURAH MOHAMMED JAFAR AL ABDULJABAR","speciality":"","qty":41.25},{"mrn":"292942","name":"ZAHRA ABDULLAH EISA ALMUSALAM","speciality":"","qty":41.25},{"mrn":"646498","name":"ZAHRA MAHDI NASSER ALSHUWAYKI","speciality":"","qty":41.25},{"mrn":"825827","name":"SUKYINAH ABDRABALHASSAN A ALZOORI","speciality":"","qty":41.25},{"mrn":"553115","name":"KAWTHAR ABDULADHEM A ALABDULRAZAQ","speciality":"","qty":41.25},{"mrn":"305911","name":"ZAHRA ALI ABDALLA AL THONAIAN","speciality":"","qty":41.25},{"mrn":"237852","name":"BEDOOR ALI N AL QAWZ","speciality":"","qty":41.25}]},{"drug":"OMEPRAZOLE - OMERAL 20 MG CAPSULE-BOX100 -TRD","patients":15,"qty":600.0,"mrns":["77885","285234","187515","237300","262001","752881","777279","543833","420058","4307","791205","73037","80054","845960","394975"],"avg":40.0,"patientRows":[{"mrn":"77885","name":"MANSOOR AHMED BINHAMAD AL HAMAD","speciality":"","qty":40.0},{"mrn":"285234","name":"YASER HAMZA ABD EL KARIM AL DARWEISH","speciality":"","qty":40.0},{"mrn":"187515","name":"ZAHRA SALEH MOHAMMED ALABDULAL","speciality":"","qty":40.0},{"mrn":"237300","name":"ZAKIAH ABDULLAH HUSSAIN AL ARIDH","speciality":"","qty":40.0},{"mrn":"262001","name":"MUGEEB HASSAN M AL DARWEESH","speciality":"","qty":40.0},{"mrn":"752881","name":"MUIDH BIN MOUSA BIN AWADH ALRIBI","speciality":"","qty":40.0},{"mrn":"777279","name":"FATEMAH FARHAN ABDALLA ALSUFYANI","speciality":"","qty":40.0},{"mrn":"543833","name":"TAHER AHMED ABDULMOHSEN AL NAMER","speciality":"","qty":40.0},{"mrn":"420058","name":"KHADIJAH ABDULLAH E ALQATARI","speciality":"","qty":40.0},{"mrn":"4307","name":"ZAHRA SALEH AHMED ALSALAM","speciality":"","qty":40.0},{"mrn":"791205","name":"DALAL ADEL  NASER","speciality":"","qty":40.0},{"mrn":"73037","name":"AHMED SAUD SOLIMAN AL HAJHOOJ","speciality":"","qty":40.0},{"mrn":"80054","name":"DALIL NASSER FARAAG ALHAJRI","speciality":"","qty":40.0},{"mrn":"845960","name":"RAMETE KURIKURA  WAKERA","speciality":"","qty":40.0},{"mrn":"394975","name":"ALI MAHDI AHMED ALBANAI","speciality":"","qty":40.0}]},{"drug":"FUROSEMIDE - DIUSEMIDE 40 MG TABLET -TRD","patients":12,"qty":555.0,"mrns":["528394","735217","12179","777279","4307","275220","429955","326326","40859","90180","80054","250374"],"avg":46.25,"patientRows":[{"mrn":"528394","name":"FAISAL ABDALLA AHMED ALJISHI","speciality":"","qty":46.25},{"mrn":"735217","name":"LAILA ALI BIN RADHI ALALWAN","speciality":"","qty":46.25},{"mrn":"12179","name":"LAILA SAEED ABDALLA ALKHALAF","speciality":"","qty":46.25},{"mrn":"777279","name":"FATEMAH FARHAN ABDALLA ALSUFYANI","speciality":"","qty":46.25},{"mrn":"4307","name":"ZAHRA SALEH AHMED ALSALAM","speciality":"","qty":46.25},{"mrn":"275220","name":"HUSSAIN ALI BIN ABDULLAH ALMARHOON","speciality":"","qty":46.25},{"mrn":"429955","name":"MAHDY SALEH ABDALLA ALMADEH","speciality":"","qty":46.25},{"mrn":"326326","name":"TAIBAH  MOHAMMEDALI ALABDRABALNABI","speciality":"","qty":46.25},{"mrn":"40859","name":"ALI HASSAN YOSEF ALJANABI","speciality":"","qty":46.25},{"mrn":"90180","name":"ALI ABDULLAH A ALREBH","speciality":"","qty":46.25},{"mrn":"80054","name":"DALIL NASSER FARAAG ALHAJRI","speciality":"","qty":46.25},{"mrn":"250374","name":"ZAHRA SALEH HUSEN ALSAFFAR","speciality":"","qty":46.25}]},{"drug":"levETIRAcetam - EPITAM 100 MG/ ML IN 150 ML  BOTTLE -TRD","patients":2,"qty":542.0,"mrns":["606112","775927"],"avg":271.0,"patientRows":[{"mrn":"606112","name":"WEJDAN MOHAMMED ALI HAKAMI","speciality":"","qty":271.0},{"mrn":"775927","name":"SAKINAH MAHER SALEH AL HAMMADI","speciality":"","qty":271.0}]},{"drug":"metFORMIN XR - GLUCOPHAGE XR 750 MG TABLET -TRD","patients":7,"qty":510.0,"mrns":["5913","754739","543833","172263","140669","90180","551625"],"avg":72.86,"patientRows":[{"mrn":"5913","name":"NAGYA ALI HUSEN ALHAKIM","speciality":"","qty":72.86},{"mrn":"754739","name":"MOHAMMED HASSAN H ALHAKIM","speciality":"","qty":72.86},{"mrn":"543833","name":"TAHER AHMED ABDULMOHSEN AL NAMER","speciality":"","qty":72.86},{"mrn":"172263","name":"ASADIYYAH ABDULLAH Abudalla ALFASHKHI","speciality":"","qty":72.86},{"mrn":"140669","name":"SHOWQI JASSIM ABDULLAH SHUWAIKHAT","speciality":"","qty":72.86},{"mrn":"90180","name":"ALI ABDULLAH A ALREBH","speciality":"","qty":72.86},{"mrn":"551625","name":"KHADIJAH HASSAN IBRAHIM ALGHAZAL","speciality":"","qty":72.86}]},{"drug":"Omeprazole-OMERAL-20 MG CAP.","patients":13,"qty":480.0,"mrns":["67986","5913","44431","757251","38868","299643","143530","671288","716501","119072","25328","476484","429955"],"avg":36.92,"patientRows":[{"mrn":"67986","name":"MOHAMMADHASSAN REDHEY SALMAN ALBYABI","speciality":"","qty":36.92},{"mrn":"5913","name":"NAGYA ALI HUSEN ALHAKIM","speciality":"","qty":36.92},{"mrn":"44431","name":"MASOUMA ABDULLAH A ALMAHROOS","speciality":"","qty":36.92},{"mrn":"757251","name":"SHAIKHAH ESSA MUBARAK ALBUAINAIN","speciality":"","qty":36.92},{"mrn":"38868","name":"LOLO RADI S ALBASHRAWI","speciality":"","qty":36.92},{"mrn":"299643","name":"MASOUMAH AHMED ABDALLA ALJUMAEI","speciality":"","qty":36.92},{"mrn":"143530","name":"SADIQAH AHMED A AL NAJI","speciality":"","qty":36.92},{"mrn":"671288","name":"FATIMAH SALEH A ALMOMEN","speciality":"","qty":36.92},{"mrn":"716501","name":"SHARIFAH KHALID HUSSAIN ALSHAMMARI","speciality":"","qty":36.92},{"mrn":"119072","name":"MOHAMMAD ABDULAH MOHAMMAD alqawas","speciality":"","qty":36.92},{"mrn":"25328","name":"AFAF AHMAD SALEH AL ALI","speciality":"","qty":36.92},{"mrn":"476484","name":"AMIRAH SALEH H ALALSHAIKH","speciality":"","qty":36.92},{"mrn":"429955","name":"MAHDY SALEH ABDALLA ALMADEH","speciality":"","qty":36.92}]},{"drug":"SEVELAMER CARBONATE - RENAPAT 800 MG TABLET -TRD","patients":3,"qty":450.0,"mrns":["380333","798069","791205"],"avg":150.0,"patientRows":[{"mrn":"380333","name":"FAKHRIAH MOHAMMED AHMED ALHASHIM","speciality":"","qty":150.0},{"mrn":"798069","name":"ZAINAB ALI ABDALLA ALQUDAIHI","speciality":"","qty":150.0},{"mrn":"791205","name":"DALAL ADEL  NASER","speciality":"","qty":150.0}]},{"drug":"CHOLECALCIFEROL; VITAMIN D3-RONZAVIT 1,000 UNIT CAPSULE -TRD","patients":13,"qty":420.0,"mrns":["203419","679656","52001","41318","541502","564344","725751","749521","31933","519197","646498","825827","553115"],"avg":32.31,"patientRows":[{"mrn":"203419","name":"SAKINAH AHMED JAFER ALMADN","speciality":"","qty":32.31},{"mrn":"679656","name":"HUSEN IBRAHIM NOUH SHAMIA","speciality":"","qty":32.31},{"mrn":"52001","name":"MASUMAH YOUSEF REDHEY ALHELAIL","speciality":"","qty":32.31},{"mrn":"41318","name":"MASOUMAH IBRAHIM Y ALJAROODI","speciality":"","qty":32.31},{"mrn":"541502","name":"HANADI JAAFER SALEH ALBAHRANI","speciality":"","qty":32.31},{"mrn":"564344","name":"SADIQ HASSAN E AL DUBAISI","speciality":"","qty":32.31},{"mrn":"725751","name":"REEM BADER TURKI ALKHALDI","speciality":"","qty":32.31},{"mrn":"749521","name":"ZAHRA MOHAMMED HABEB ALHALAL","speciality":"","qty":32.31},{"mrn":"31933","name":"ZAINAB MOHAMMED ALI AMMAR","speciality":"","qty":32.31},{"mrn":"519197","name":"ZAINAB ALI A ALMATAR","speciality":"","qty":32.31},{"mrn":"646498","name":"ZAHRA MAHDI NASSER ALSHUWAYKI","speciality":"","qty":32.31},{"mrn":"825827","name":"SUKYINAH ABDRABALHASSAN A ALZOORI","speciality":"","qty":32.31},{"mrn":"553115","name":"KAWTHAR ABDULADHEM A ALABDULRAZAQ","speciality":"","qty":32.31}]},{"drug":"prednisoLONE - GUPISONE 5 MG TABLET -TRD","patients":8,"qty":420.0,"mrns":["38605","295360","607308","129057","716501","25328","73037","305911"],"avg":52.5,"patientRows":[{"mrn":"38605","name":"HUDA AJEEB SALEH ALHASSAN","speciality":"","qty":52.5},{"mrn":"295360","name":"GHADAH MAKKI AHMED AL RAMADAN","speciality":"","qty":52.5},{"mrn":"607308","name":"FATIMAH MOHAMMED SAEED ALAWOA","speciality":"","qty":52.5},{"mrn":"129057","name":"MASOUMAH SALMAN IBRAHIM ALMARHOON","speciality":"","qty":52.5},{"mrn":"716501","name":"SHARIFAH KHALID HUSSAIN ALSHAMMARI","speciality":"","qty":52.5},{"mrn":"25328","name":"AFAF AHMAD SALEH AL ALI","speciality":"","qty":52.5},{"mrn":"73037","name":"AHMED SAUD SOLIMAN AL HAJHOOJ","speciality":"","qty":52.5},{"mrn":"305911","name":"ZAHRA ALI ABDALLA AL THONAIAN","speciality":"","qty":52.5}]},{"drug":"LevETIRAcetam - VITRAM 500 MG F.C TABLET -TRD","patients":3,"qty":420.0,"mrns":["253914","176610","463443"],"avg":140.0,"patientRows":[{"mrn":"253914","name":"ZAINAB HUSSAIN SALEH Al mrabit","speciality":"","qty":140.0},{"mrn":"176610","name":"LATIFA ABDULLAH A THABET","speciality":"","qty":140.0},{"mrn":"463443","name":"JAFAR MOUSA JAFAR AL SHANAR","speciality":"","qty":140.0}]},{"drug":"MELOXICAM - OXIMAL 15 MG TABLET -TRD","patients":13,"qty":390.0,"mrns":["718589","646292","159750","474896","59801","107800","14450","340833","221881","304689","844610","369912","173767"],"avg":30.0,"patientRows":[{"mrn":"718589","name":"AWATEF IBRAHIM AHMED ALGHAFLI","speciality":"","qty":30.0},{"mrn":"646292","name":"MNAHIL SHAMSELDEEN MOHAMED SULIMAN","speciality":"","qty":30.0},{"mrn":"159750","name":"FATMA HASSAN ALI ALDOBASE","speciality":"","qty":30.0},{"mrn":"474896","name":"HABEB ABD EL MEGED ADB EL MOHASSEN ALZAKI","speciality":"","qty":30.0},{"mrn":"59801","name":"HUSSAIN ABDRABALRASOOL YOSEF AL HAJJI","speciality":"","qty":30.0},{"mrn":"107800","name":"LAILAH MAKI Y AL KHMISS","speciality":"","qty":30.0},{"mrn":"14450","name":"AMERAH ALI REDHEY ALDAMEN","speciality":"","qty":30.0},{"mrn":"340833","name":"RABAB ABASS IBRAHIM AL HUSEN","speciality":"","qty":30.0},{"mrn":"221881","name":"ZAINAB ALI I AL MBEREEK","speciality":"","qty":30.0},{"mrn":"304689","name":"LAYLA ABDULLAH ABD EL KARIM ALJOMAIA","speciality":"","qty":30.0},{"mrn":"844610","name":"ZEESHAN   HAIDER","speciality":"","qty":30.0},{"mrn":"369912","name":"FATMA HASSAN SALEH ALMARHOON","speciality":"","qty":30.0},{"mrn":"173767","name":"ADEL EISSA ABDULKAREEM ALFARKI","speciality":"","qty":30.0}]},{"drug":"AMLODIPINE-LODIPAM-5 MG TAB (COAT)","patients":8,"qty":390.0,"mrns":["601743","5913","754739","462235","429955","614916","40859","436538"],"avg":48.75,"patientRows":[{"mrn":"601743","name":"ALI HASSAN A ALZEENALDEEN","speciality":"","qty":48.75},{"mrn":"5913","name":"NAGYA ALI HUSEN ALHAKIM","speciality":"","qty":48.75},{"mrn":"754739","name":"MOHAMMED HASSAN H ALHAKIM","speciality":"","qty":48.75},{"mrn":"462235","name":"AFIFAH ALI MOBARK ALJESHI","speciality":"","qty":48.75},{"mrn":"429955","name":"MAHDY SALEH ABDALLA ALMADEH","speciality":"","qty":48.75},{"mrn":"614916","name":"FATIMAH ALI H ALABANDI","speciality":"","qty":48.75},{"mrn":"40859","name":"ALI HASSAN YOSEF ALJANABI","speciality":"","qty":48.75},{"mrn":"436538","name":"ZAKI ABDULLAH SHARAF ALHASHIM","speciality":"","qty":48.75}]},{"drug":"ESOMEPRAZOLE - ESOPOLE 20 MG CAPSULE -TRD","patients":7,"qty":384.0,"mrns":["747130","152039","165412","300944","555541","139271","208863"],"avg":54.86,"patientRows":[{"mrn":"747130","name":"ZOHAIR RIDA MOHAMMED AL ATIYA","speciality":"","qty":54.86},{"mrn":"152039","name":"MALIKA ALI QAZEM SONBEL","speciality":"","qty":54.86},{"mrn":"165412","name":"ZAHRA REDHEY JAWAD ALQUNIZI","speciality":"","qty":54.86},{"mrn":"300944","name":"AREJJ HASSAN M ALABADI","speciality":"","qty":54.86},{"mrn":"555541","name":"REEM MAHMOUD QASSIM ALTOWAL","speciality":"","qty":54.86},{"mrn":"139271","name":"MOHAMMED ABDULLAH HASSAN AL NAS","speciality":"","qty":54.86},{"mrn":"208863","name":"SAJJAD ZAKI AHMAD ALREBH","speciality":"","qty":54.86}]},{"drug":"PARACETAMOL - PANADREX 500 MG TABLET -TRD","patients":4,"qty":384.0,"mrns":["46440","671288","413371","107800"],"avg":96.0,"patientRows":[{"mrn":"46440","name":"ZALIKHAH ABDULLAH A ALDHAMEN","speciality":"","qty":96.0},{"mrn":"671288","name":"FATIMAH SALEH A ALMOMEN","speciality":"","qty":96.0},{"mrn":"413371","name":"FATMA ABDULJALEEL IBRAHIM ALMESHAMA","speciality":"","qty":96.0},{"mrn":"107800","name":"LAILAH MAKI Y AL KHMISS","speciality":"","qty":96.0}]},{"drug":"PROPRANOLOL - INDICARDIN 10 MG TABLET -TRD","patients":4,"qty":360.0,"mrns":["285234","203419","144764","148644"],"avg":90.0,"patientRows":[{"mrn":"285234","name":"YASER HAMZA ABD EL KARIM AL DARWEISH","speciality":"","qty":90.0},{"mrn":"203419","name":"SAKINAH AHMED JAFER ALMADN","speciality":"","qty":90.0},{"mrn":"144764","name":"KAWTHER MOHAMMED H ALKHADHRAWI","speciality":"","qty":90.0},{"mrn":"148644","name":"MASOOMA YOUSIF A ALAWA","speciality":"","qty":90.0}]},{"drug":"TOPIRAMATE - IPRAMAX  25 MG F.C. TABLET -TRD","patients":2,"qty":360.0,"mrns":["148644","140669"],"avg":180.0,"patientRows":[{"mrn":"148644","name":"MASOOMA YOUSIF A ALAWA","speciality":"","qty":180.0},{"mrn":"140669","name":"SHOWQI JASSIM ABDULLAH SHUWAIKHAT","speciality":"","qty":180.0}]},{"drug":"SODIUM BICARBONATE -NA BICA 325 MG TABLET -TRD","patients":1,"qty":360.0,"mrns":["4307"],"avg":360.0,"patientRows":[{"mrn":"4307","name":"ZAHRA SALEH AHMED ALSALAM","speciality":"","qty":360.0}]},{"drug":"CARVEDILOL- CARVIDOL 25 MG TABLET -TRD","patients":6,"qty":330.0,"mrns":["67986","798069","172263","169014","80054","250374"],"avg":55.0,"patientRows":[{"mrn":"67986","name":"MOHAMMADHASSAN REDHEY SALMAN ALBYABI","speciality":"","qty":55.0},{"mrn":"798069","name":"ZAINAB ALI ABDALLA ALQUDAIHI","speciality":"","qty":55.0},{"mrn":"172263","name":"ASADIYYAH ABDULLAH Abudalla ALFASHKHI","speciality":"","qty":55.0},{"mrn":"169014","name":"NAJMA SALEH M ALJARAD","speciality":"","qty":55.0},{"mrn":"80054","name":"DALIL NASSER FARAAG ALHAJRI","speciality":"","qty":55.0},{"mrn":"250374","name":"ZAHRA SALEH HUSEN ALSAFFAR","speciality":"","qty":55.0}]},{"drug":"Iron hydroxide polymaltose ;Folic acid-FEROSE F-100 mg;350mcg TAB (CHEW)","patients":7,"qty":300.0,"mrns":["295360","22646","400731","503568","271377","825827","553115"],"avg":42.86,"patientRows":[{"mrn":"295360","name":"GHADAH MAKKI AHMED AL RAMADAN","speciality":"","qty":42.86},{"mrn":"22646","name":"KHADIJAH JASEM MOHD HSAN ALNAZAH","speciality":"","qty":42.86},{"mrn":"400731","name":"FATMA FAYEZ HUSEN AL SHHRANY","speciality":"","qty":42.86},{"mrn":"503568","name":"ZAHRA JASSIM SALEM ALMUZARRA","speciality":"","qty":42.86},{"mrn":"271377","name":"HOURAH MOHAMMED JAFAR AL ABDULJABAR","speciality":"","qty":42.86},{"mrn":"825827","name":"SUKYINAH ABDRABALHASSAN A ALZOORI","speciality":"","qty":42.86},{"mrn":"553115","name":"KAWTHAR ABDULADHEM A ALABDULRAZAQ","speciality":"","qty":42.86}]},{"drug":"BACLOFEN-BACLON 10 MG TABLET -TRD","patients":5,"qty":300.0,"mrns":["260514","88851","379634","507297","462186"],"avg":60.0,"patientRows":[{"mrn":"260514","name":"SADIA HABIB A ALHMAM","speciality":"","qty":60.0},{"mrn":"88851","name":"MONA ABDULKAREEM M AL KHATER","speciality":"","qty":60.0},{"mrn":"379634","name":"MOHSEN ABBAS A AL DABEL","speciality":"","qty":60.0},{"mrn":"507297","name":"BADRIYAH IBRAHIM ABDALLA MALALLAH","speciality":"","qty":60.0},{"mrn":"462186","name":"FATEMAH MOHAMMED A Al dawad","speciality":"","qty":60.0}]},{"drug":"FOLIC ACID-BEFOLVIT-1 MG TABLET","patients":10,"qty":295.0,"mrns":["38605","295946","5913","260995","4307","265940","25328","40859","46179","292942"],"avg":29.5,"patientRows":[{"mrn":"38605","name":"HUDA AJEEB SALEH ALHASSAN","speciality":"","qty":29.5},{"mrn":"295946","name":"Nawal Abdulrasoul Radi Alabdulrasoul","speciality":"","qty":29.5},{"mrn":"5913","name":"NAGYA ALI HUSEN ALHAKIM","speciality":"","qty":29.5},{"mrn":"260995","name":"AFAF HUSEN JUBRAN HAZAZY","speciality":"","qty":29.5},{"mrn":"4307","name":"ZAHRA SALEH AHMED ALSALAM","speciality":"","qty":29.5},{"mrn":"265940","name":"ALAWIYYAH BAQI BAQER AL MOQBEL","speciality":"","qty":29.5},{"mrn":"25328","name":"AFAF AHMAD SALEH AL ALI","speciality":"","qty":29.5},{"mrn":"40859","name":"ALI HASSAN YOSEF ALJANABI","speciality":"","qty":29.5},{"mrn":"46179","name":"SAEEDAH AHMED BIN MOHAMMED ALFARAG","speciality":"","qty":29.5},{"mrn":"292942","name":"ZAHRA ABDULLAH EISA ALMUSALAM","speciality":"","qty":29.5}]},{"drug":"PERINDOPRIL-TENORYL-5 MG TAB","patients":8,"qty":270.0,"mrns":["67986","227869","543833","172263","143530","75779","436538","80730"],"avg":33.75,"patientRows":[{"mrn":"67986","name":"MOHAMMADHASSAN REDHEY SALMAN ALBYABI","speciality":"","qty":33.75},{"mrn":"227869","name":"ABDULMABUD ABDULMOHSEN A ALFARAJ","speciality":"","qty":33.75},{"mrn":"543833","name":"TAHER AHMED ABDULMOHSEN AL NAMER","speciality":"","qty":33.75},{"mrn":"172263","name":"ASADIYYAH ABDULLAH Abudalla ALFASHKHI","speciality":"","qty":33.75},{"mrn":"143530","name":"SADIQAH AHMED A AL NAJI","speciality":"","qty":33.75},{"mrn":"75779","name":"JEHAN MOHAMMED ABASS AL AHMED","speciality":"","qty":33.75},{"mrn":"436538","name":"ZAKI ABDULLAH SHARAF ALHASHIM","speciality":"","qty":33.75},{"mrn":"80730","name":"MARIAM ALI MOHAMMAD ALKAAIBI","speciality":"","qty":33.75}]},{"drug":"VALSARTAN - TABUVAN 80 MG F.C TABLET -TRD","patients":7,"qty":270.0,"mrns":["5913","239390","22646","395112","744382","40859","140669"],"avg":38.57,"patientRows":[{"mrn":"5913","name":"NAGYA ALI HUSEN ALHAKIM","speciality":"","qty":38.57},{"mrn":"239390","name":"ZANAAB ALI AHMED ALABAS","speciality":"","qty":38.57},{"mrn":"22646","name":"KHADIJAH JASEM MOHD HSAN ALNAZAH","speciality":"","qty":38.57},{"mrn":"395112","name":"HUDA HASHEM HUSEN ALQHADRAWI","speciality":"","qty":38.57},{"mrn":"744382","name":"KHATUN QAZEM YOSEF ALALAWI","speciality":"","qty":38.57},{"mrn":"40859","name":"ALI HASSAN YOSEF ALJANABI","speciality":"","qty":38.57},{"mrn":"140669","name":"SHOWQI JASSIM ABDULLAH SHUWAIKHAT","speciality":"","qty":38.57}]},{"drug":"POTASSIUM CHLORIDE XR- STRIDES INC 600 MG (8 mEq) TAB -TRD","patients":1,"qty":270.0,"mrns":["72521"],"avg":270.0,"patientRows":[{"mrn":"72521","name":"ABDALHAI ABBAS ALI AL QMBAR","speciality":"","qty":270.0}]},{"drug":"ASPIRIN, ASA-BAYER ASPIRIN 100 MG TABLET","patients":10,"qty":266.0,"mrns":["67986","33225","239390","741305","279607","113915","299643","143530","429955","14387"],"avg":26.6,"patientRows":[{"mrn":"67986","name":"MOHAMMADHASSAN REDHEY SALMAN ALBYABI","speciality":"","qty":26.6},{"mrn":"33225","name":"ALI ABDULBAQI BN ALI ABOELSAOUD","speciality":"","qty":26.6},{"mrn":"239390","name":"ZANAAB ALI AHMED ALABAS","speciality":"","qty":26.6},{"mrn":"741305","name":"SAEED SALMAN M AL ABDULAAL","speciality":"","qty":26.6},{"mrn":"279607","name":"SHAIMA ABDRABALAMEER ABDALLA KHALAF","speciality":"","qty":26.6},{"mrn":"113915","name":"BAHEYAH AHMAD HASSAN AL GHAZWI","speciality":"","qty":26.6},{"mrn":"299643","name":"MASOUMAH AHMED ABDALLA ALJUMAEI","speciality":"","qty":26.6},{"mrn":"143530","name":"SADIQAH AHMED A AL NAJI","speciality":"","qty":26.6},{"mrn":"429955","name":"MAHDY SALEH ABDALLA ALMADEH","speciality":"","qty":26.6},{"mrn":"14387","name":"HUSEN AHMED HUSEN HAMEEDI","speciality":"","qty":26.6}]},{"drug":"carBAMazepine - CARBATOL 200 MG TABLET-BOX500 -TRD","patients":5,"qty":260.0,"mrns":["680590","227869","547638","55568","207856"],"avg":52.0,"patientRows":[{"mrn":"680590","name":"MADINAH MANSOUR ABDALLA KALW","speciality":"","qty":52.0},{"mrn":"227869","name":"ABDULMABUD ABDULMOHSEN A ALFARAJ","speciality":"","qty":52.0},{"mrn":"547638","name":"ALI HUSEN MOHAMMED AL SHARAF","speciality":"","qty":52.0},{"mrn":"55568","name":"AMIRA HASSAN MOHAMMAD ALGHORYAFI","speciality":"","qty":52.0},{"mrn":"207856","name":"SHARAF ALAWI BIN RADHI AL KHADHRAWI","speciality":"","qty":52.0}]},{"drug":"APIXABAN - XCARD 5 MG F.C TABLET -TRD","patients":4,"qty":240.0,"mrns":["433975","735217","38868","744382"],"avg":60.0,"patientRows":[{"mrn":"433975","name":"EISA MANSOR SALEEM AL AADAM","speciality":"","qty":60.0},{"mrn":"735217","name":"LAILA ALI BIN RADHI ALALWAN","speciality":"","qty":60.0},{"mrn":"38868","name":"LOLO RADI S ALBASHRAWI","speciality":"","qty":60.0},{"mrn":"744382","name":"KHATUN QAZEM YOSEF ALALAWI","speciality":"","qty":60.0}]},{"drug":"VALPROIC ACID - DEPAKINE CHRONO 500 MG TABLET -TRD","patients":3,"qty":240.0,"mrns":["43277","260995","198028"],"avg":80.0,"patientRows":[{"mrn":"43277","name":"SALEH ABDULRAOUF ABDULLAH ALNAJAR","speciality":"","qty":80.0},{"mrn":"260995","name":"AFAF HUSEN JUBRAN HAZAZY","speciality":"","qty":80.0},{"mrn":"198028","name":"ALI MOHAMMAD SALEH ALSHERYAWE","speciality":"","qty":80.0}]},{"drug":"MESALAZINE - PENTASA 500 MG SLOW-RELEASE TABLET -TRD","patients":2,"qty":240.0,"mrns":["564344","140669"],"avg":120.0,"patientRows":[{"mrn":"564344","name":"SADIQ HASSAN E AL DUBAISI","speciality":"","qty":120.0},{"mrn":"140669","name":"SHOWQI JASSIM ABDULLAH SHUWAIKHAT","speciality":"","qty":120.0}]},{"drug":"SITagliptin- JULEEN 100 MG F.C TABLET -TRD","patients":5,"qty":210.0,"mrns":["543833","626316","172263","80054","551625"],"avg":42.0,"patientRows":[{"mrn":"543833","name":"TAHER AHMED ABDULMOHSEN AL NAMER","speciality":"","qty":42.0},{"mrn":"626316","name":"MASOMAH ALI MOHAMMED AL DARWISH","speciality":"","qty":42.0},{"mrn":"172263","name":"ASADIYYAH ABDULLAH Abudalla ALFASHKHI","speciality":"","qty":42.0},{"mrn":"80054","name":"DALIL NASSER FARAAG ALHAJRI","speciality":"","qty":42.0},{"mrn":"551625","name":"KHADIJAH HASSAN IBRAHIM ALGHAZAL","speciality":"","qty":42.0}]},{"drug":"ATORVASTATIN-ATORVA 20 MG F.C TABLET - BOX130 -TRD","patients":4,"qty":210.0,"mrns":["14387","140669","80054","551625"],"avg":52.5,"patientRows":[{"mrn":"14387","name":"HUSEN AHMED HUSEN HAMEEDI","speciality":"","qty":52.5},{"mrn":"140669","name":"SHOWQI JASSIM ABDULLAH SHUWAIKHAT","speciality":"","qty":52.5},{"mrn":"80054","name":"DALIL NASSER FARAAG ALHAJRI","speciality":"","qty":52.5},{"mrn":"551625","name":"KHADIJAH HASSAN IBRAHIM ALGHAZAL","speciality":"","qty":52.5}]},{"drug":"ASPIRIN -BAYER 100 MG F.C TABLET -TRD","patients":7,"qty":200.0,"mrns":["38605","543833","172263","140669","436538","302366","250374"],"avg":28.57,"patientRows":[{"mrn":"38605","name":"HUDA AJEEB SALEH ALHASSAN","speciality":"","qty":28.57},{"mrn":"543833","name":"TAHER AHMED ABDULMOHSEN AL NAMER","speciality":"","qty":28.57},{"mrn":"172263","name":"ASADIYYAH ABDULLAH Abudalla ALFASHKHI","speciality":"","qty":28.57},{"mrn":"140669","name":"SHOWQI JASSIM ABDULLAH SHUWAIKHAT","speciality":"","qty":28.57},{"mrn":"436538","name":"ZAKI ABDULLAH SHARAF ALHASHIM","speciality":"","qty":28.57},{"mrn":"302366","name":"EMAN MOHAMMAD MAKKI ALMUKHTAR","speciality":"","qty":28.57},{"mrn":"250374","name":"ZAHRA SALEH HUSEN ALSAFFAR","speciality":"","qty":28.57}]},{"drug":"NOVO-FINE NEEDLE 6 MM","patients":2,"qty":200.0,"mrns":["110122","153535"],"avg":100.0,"patientRows":[{"mrn":"110122","name":"ABDULAH WAHAB ABDULAH SUBAIRI","speciality":"","qty":100.0},{"mrn":"153535","name":"HUSSAIN BIN MANSOUR JAWAD ABU JUAYD","speciality":"","qty":100.0}]},{"drug":"LEVODOPA; BENSERAZIDE  - MADOPAR 200 MG; 50 MG  TABLET -TRD","patients":1,"qty":200.0,"mrns":["40194"],"avg":200.0,"patientRows":[{"mrn":"40194","name":"HUSSAIN ABDULRAZAQ S ABUJAID","speciality":"","qty":200.0}]},{"drug":"PHENYTOIN - EPANUTIN 100 MG CAPSULE -TRD","patients":2,"qty":190.0,"mrns":["253914","74804"],"avg":95.0,"patientRows":[{"mrn":"253914","name":"ZAINAB HUSSAIN SALEH Al mrabit","speciality":"","qty":95.0},{"mrn":"74804","name":"AHMED MOHAMMED S ASAEED","speciality":"","qty":95.0}]},{"drug":"MULTIVITAMINS ADULT- AR VITA TABLET -TRD","patients":6,"qty":180.0,"mrns":["260995","777279","113915","208198","355198","347830"],"avg":30.0,"patientRows":[{"mrn":"260995","name":"AFAF HUSEN JUBRAN HAZAZY","speciality":"","qty":30.0},{"mrn":"777279","name":"FATEMAH FARHAN ABDALLA ALSUFYANI","speciality":"","qty":30.0},{"mrn":"113915","name":"BAHEYAH AHMAD HASSAN AL GHAZWI","speciality":"","qty":30.0},{"mrn":"208198","name":"KHADIJA ABDULLAH MAHDY AL TOFEEQ","speciality":"","qty":30.0},{"mrn":"355198","name":"FATIMAH ABDULWAHED MAHDI ALZAIN","speciality":"","qty":30.0},{"mrn":"347830","name":"SAJA SALMAN H ALNASSER","speciality":"","qty":30.0}]},{"drug":"ROSUVASTATIN-IVARIN-20 MG TAB","patients":6,"qty":180.0,"mrns":["67986","239390","21278","38868","113915","429955"],"avg":30.0,"patientRows":[{"mrn":"67986","name":"MOHAMMADHASSAN REDHEY SALMAN ALBYABI","speciality":"","qty":30.0},{"mrn":"239390","name":"ZANAAB ALI AHMED ALABAS","speciality":"","qty":30.0},{"mrn":"21278","name":"HUSAH ALI SALEH AL FAHAD","speciality":"","qty":30.0},{"mrn":"38868","name":"LOLO RADI S ALBASHRAWI","speciality":"","qty":30.0},{"mrn":"113915","name":"BAHEYAH AHMAD HASSAN AL GHAZWI","speciality":"","qty":30.0},{"mrn":"429955","name":"MAHDY SALEH ABDALLA ALMADEH","speciality":"","qty":30.0}]},{"drug":"bisoPROLOL-SELECTA 5 MG TAB","patients":6,"qty":170.0,"mrns":["433975","464987","744382","140954","143530","429955"],"avg":28.33,"patientRows":[{"mrn":"433975","name":"EISA MANSOR SALEEM AL AADAM","speciality":"","qty":28.33},{"mrn":"464987","name":"HUDA YOSEF  AL ZAWAD","speciality":"","qty":28.33},{"mrn":"744382","name":"KHATUN QAZEM YOSEF ALALAWI","speciality":"","qty":28.33},{"mrn":"140954","name":"FATIMAH ALI ABDALLA AL SALEM","speciality":"","qty":28.33},{"mrn":"143530","name":"SADIQAH AHMED A AL NAJI","speciality":"","qty":28.33},{"mrn":"429955","name":"MAHDY SALEH ABDALLA ALMADEH","speciality":"","qty":28.33}]},{"drug":"TAMSULOSIN - PROSTA 0.4 MG P.R TABLET -TRD","patients":5,"qty":150.0,"mrns":["125153","260577","606305","250245","36291"],"avg":30.0,"patientRows":[{"mrn":"125153","name":"HASSAN SALEH HASSAN Alqryr","speciality":"","qty":30.0},{"mrn":"260577","name":"BADR MANSOUR HABLAN ALSEDAYR","speciality":"","qty":30.0},{"mrn":"606305","name":"SALMAN JAWAD SALMAN ALDAALOUJ","speciality":"","qty":30.0},{"mrn":"250245","name":"MOHAMMED ALI H AL ASWAD","speciality":"","qty":30.0},{"mrn":"36291","name":"MIRZA AHMED MNSSOR ALMAKHMAL","speciality":"","qty":30.0}]},{"drug":"CALCIUM CARBONATE-CARBOSET-600 MG TAB","patients":4,"qty":150.0,"mrns":["129057","716501","25328","493845"],"avg":37.5,"patientRows":[{"mrn":"129057","name":"MASOUMAH SALMAN IBRAHIM ALMARHOON","speciality":"","qty":37.5},{"mrn":"716501","name":"SHARIFAH KHALID HUSSAIN ALSHAMMARI","speciality":"","qty":37.5},{"mrn":"25328","name":"AFAF AHMAD SALEH AL ALI","speciality":"","qty":37.5},{"mrn":"493845","name":"MALEEHAH SALMAN GABAL GABAL","speciality":"","qty":37.5}]},{"drug":"ROSUVASTATIN - IVARIN 20 MG F.C TABLET -TRD","patients":4,"qty":150.0,"mrns":["172263","436538","80730","250374"],"avg":37.5,"patientRows":[{"mrn":"172263","name":"ASADIYYAH ABDULLAH Abudalla ALFASHKHI","speciality":"","qty":37.5},{"mrn":"436538","name":"ZAKI ABDULLAH SHARAF ALHASHIM","speciality":"","qty":37.5},{"mrn":"80730","name":"MARIAM ALI MOHAMMAD ALKAAIBI","speciality":"","qty":37.5},{"mrn":"250374","name":"ZAHRA SALEH HUSEN ALSAFFAR","speciality":"","qty":37.5}]},{"drug":"AMITRIPTYLINE- ALATRIPT 25 MG TABLET  -TRD","patients":3,"qty":150.0,"mrns":["285234","457745","45534"],"avg":50.0,"patientRows":[{"mrn":"285234","name":"YASER HAMZA ABD EL KARIM AL DARWEISH","speciality":"","qty":50.0},{"mrn":"457745","name":"SALEH ABDULLAH M AL DRWISH","speciality":"","qty":50.0},{"mrn":"45534","name":"MOUSA YONES HUSEN AL HERZ","speciality":"","qty":50.0}]},{"drug":"ATORVASTATIN-ATORVA-20 MG TAB","patients":3,"qty":150.0,"mrns":["741305","744382","299643"],"avg":50.0,"patientRows":[{"mrn":"741305","name":"SAEED SALMAN M AL ABDULAAL","speciality":"","qty":50.0},{"mrn":"744382","name":"KHATUN QAZEM YOSEF ALALAWI","speciality":"","qty":50.0},{"mrn":"299643","name":"MASOUMAH AHMED ABDALLA ALJUMAEI","speciality":"","qty":50.0}]},{"drug":"NIFEdipine - ADALAT LA 30 MG TABLET -TRD","patients":3,"qty":150.0,"mrns":["4307","791205","716501"],"avg":50.0,"patientRows":[{"mrn":"4307","name":"ZAHRA SALEH AHMED ALSALAM","speciality":"","qty":50.0},{"mrn":"791205","name":"DALAL ADEL  NASER","speciality":"","qty":50.0},{"mrn":"716501","name":"SHARIFAH KHALID HUSSAIN ALSHAMMARI","speciality":"","qty":50.0}]},{"drug":"metFORMIN - GLUCARE 500 MG F.C. TABLET -TRD","patients":3,"qty":150.0,"mrns":["203419","226931","299643"],"avg":50.0,"patientRows":[{"mrn":"203419","name":"SAKINAH AHMED JAFER ALMADN","speciality":"","qty":50.0},{"mrn":"226931","name":"FADELAH ALI AHMED ALMAHOOZI","speciality":"","qty":50.0},{"mrn":"299643","name":"MASOUMAH AHMED ABDALLA ALJUMAEI","speciality":"","qty":50.0}]},{"drug":"MAGNESIUM OXIDE  - MAGLIVARA 400 MG TABLET -TRD","patients":2,"qty":130.0,"mrns":["72521","140669"],"avg":65.0,"patientRows":[{"mrn":"72521","name":"ABDALHAI ABBAS ALI AL QMBAR","speciality":"","qty":65.0},{"mrn":"140669","name":"SHOWQI JASSIM ABDULLAH SHUWAIKHAT","speciality":"","qty":65.0}]},{"drug":"levoTHYROxine-ELTROXIN-100 MCG TAB","patients":2,"qty":130.0,"mrns":["36374","678655"],"avg":65.0,"patientRows":[{"mrn":"36374","name":"ALI AHMAD ALI ALTLALWAH","speciality":"","qty":65.0},{"mrn":"678655","name":"NADA HAMOOD NAWI ALENEZI","speciality":"","qty":65.0}]},{"drug":"AMITRIPTYLINE- ALATRIPT 10 MG TABLET  -TRD","patients":4,"qty":120.0,"mrns":["747130","144764","485549","208863"],"avg":30.0,"patientRows":[{"mrn":"747130","name":"ZOHAIR RIDA MOHAMMED AL ATIYA","speciality":"","qty":30.0},{"mrn":"144764","name":"KAWTHER MOHAMMED H ALKHADHRAWI","speciality":"","qty":30.0},{"mrn":"485549","name":"LAMYA SHAREEDAH A ALNAHWI","speciality":"","qty":30.0},{"mrn":"208863","name":"SAJJAD ZAKI AHMAD ALREBH","speciality":"","qty":30.0}]},{"drug":"CETIRIZINE - CETRALON 10 MG F.C. TABLET -TRD","patients":4,"qty":120.0,"mrns":["237300","483712","614871","314118"],"avg":30.0,"patientRows":[{"mrn":"237300","name":"ZAKIAH ABDULLAH HUSSAIN AL ARIDH","speciality":"","qty":30.0},{"mrn":"483712","name":"RABAB ABDALLA AHMED ALAJAMI","speciality":"","qty":30.0},{"mrn":"614871","name":"MAHDI ALI HASSAN ALMUTAWAH","speciality":"","qty":30.0},{"mrn":"314118","name":"ZAINAB MOHAMMAD J KHATEM","speciality":"","qty":30.0}]},{"drug":"HydroxyCHLOROQUINE-PLAQUENIL- 200 MG TABLET","patients":3,"qty":120.0,"mrns":["5913","129057","716501"],"avg":40.0,"patientRows":[{"mrn":"5913","name":"NAGYA ALI HUSEN ALHAKIM","speciality":"","qty":40.0},{"mrn":"129057","name":"MASOUMAH SALMAN IBRAHIM ALMARHOON","speciality":"","qty":40.0},{"mrn":"716501","name":"SHARIFAH KHALID HUSSAIN ALSHAMMARI","speciality":"","qty":40.0}]},{"drug":"VITAMIN B1;B6;B12-TRIPLEX B-100, 200 MG, 200 MCG TAB","patients":3,"qty":120.0,"mrns":["37491","227869","344977"],"avg":40.0,"patientRows":[{"mrn":"37491","name":"HASHIM HASSAN ALI ALSAYHATI","speciality":"","qty":40.0},{"mrn":"227869","name":"ABDULMABUD ABDULMOHSEN A ALFARAJ","speciality":"","qty":40.0},{"mrn":"344977","name":"HASSAN SHAFIQ AHMAD AL KHULAIF","speciality":"","qty":40.0}]},{"drug":"AMANTADINE - PK-MERZ 100 MG TABLET  -TRD","patients":2,"qty":120.0,"mrns":["176610","9388"],"avg":60.0,"patientRows":[{"mrn":"176610","name":"LATIFA ABDULLAH A THABET","speciality":"","qty":60.0},{"mrn":"9388","name":"DALAL ALI HASSAN ALSENAN","speciality":"","qty":60.0}]},{"drug":"MELOXICAM-MOBIC-7.5 MG TAB","patients":2,"qty":120.0,"mrns":["41318","293298"],"avg":60.0,"patientRows":[{"mrn":"41318","name":"MASOUMAH IBRAHIM Y ALJAROODI","speciality":"","qty":60.0},{"mrn":"293298","name":"ZAHRA ABDULLAH ESSA AL SALEM","speciality":"","qty":60.0}]},{"drug":"PROPRANOLOL - INDICARDIN 40 MG TABLET -TRD","patients":2,"qty":120.0,"mrns":["439017","344977"],"avg":60.0,"patientRows":[{"mrn":"439017","name":"TWAH ABDRBALHUSSAIN H ABU SHLWAH","speciality":"","qty":60.0},{"mrn":"344977","name":"HASSAN SHAFIQ AHMAD AL KHULAIF","speciality":"","qty":60.0}]},{"drug":"azaTHIOprine -IMURAN 50 MG TABLET -TRD","patients":2,"qty":120.0,"mrns":["607308","140669"],"avg":60.0,"patientRows":[{"mrn":"607308","name":"FATIMAH MOHAMMED SAEED ALAWOA","speciality":"","qty":60.0},{"mrn":"140669","name":"SHOWQI JASSIM ABDULLAH SHUWAIKHAT","speciality":"","qty":60.0}]},{"drug":"BOSENTAN-GONISTA-62.5 MG TAB","patients":1,"qty":120.0,"mrns":["21278"],"avg":120.0,"patientRows":[{"mrn":"21278","name":"HUSAH ALI SALEH AL FAHAD","speciality":"","qty":120.0}]},{"drug":"CARVEDILOL- RAVILDO 6.25 MG F.C. TABLET -TRD","patients":1,"qty":120.0,"mrns":["4307"],"avg":120.0,"patientRows":[{"mrn":"4307","name":"ZAHRA SALEH AHMED ALSALAM","speciality":"","qty":120.0}]},{"drug":"MYCOPHENOLATE MOFETIL-ACCORD 500 MG F.C TABLET -TRD","patients":1,"qty":120.0,"mrns":["22646"],"avg":120.0,"patientRows":[{"mrn":"22646","name":"KHADIJAH JASEM MOHD HSAN ALNAZAH","speciality":"","qty":120.0}]},{"drug":"gliCLAzide - DIAMICRON 30 MG MR TABLET -TRD","patients":1,"qty":120.0,"mrns":["172263"],"avg":120.0,"patientRows":[{"mrn":"172263","name":"ASADIYYAH ABDULLAH Abudalla ALFASHKHI","speciality":"","qty":120.0}]},{"drug":"metFORMIN - GLUCOPHAGE 500 MG F.C TABLET -TRD","patients":1,"qty":120.0,"mrns":["80054"],"avg":120.0,"patientRows":[{"mrn":"80054","name":"DALIL NASSER FARAAG ALHAJRI","speciality":"","qty":120.0}]},{"drug":"TADALAFIL - AVIALIS 5 MG F.C. TABLET -TRD","patients":4,"qty":118.0,"mrns":["747130","250245","165125","37246"],"avg":29.5,"patientRows":[{"mrn":"747130","name":"ZOHAIR RIDA MOHAMMED AL ATIYA","speciality":"","qty":29.5},{"mrn":"250245","name":"MOHAMMED ALI H AL ASWAD","speciality":"","qty":29.5},{"mrn":"165125","name":"MAJED MANSOOR BIN SALMAN ALSAIHATI","speciality":"","qty":29.5},{"mrn":"37246","name":"ADEL SAEED IBRAHIM ALSAFFAR","speciality":"","qty":29.5}]},{"drug":"FERROUS SULFATE - FERRO TAB 200 MG TABLET -TRD","patients":4,"qty":116.0,"mrns":["320466","578725","152064","646498"],"avg":29.0,"patientRows":[{"mrn":"320466","name":"NOOR ABDULLAH MATUQ ALKHAYAT","speciality":"","qty":29.0},{"mrn":"578725","name":"ALI AHMED HAMZAH AL MUGHAYZIL","speciality":"","qty":29.0},{"mrn":"152064","name":"AZHAR MOHAMMED SALEH ALHAIZ","speciality":"","qty":29.0},{"mrn":"646498","name":"ZAHRA MAHDI NASSER ALSHUWAYKI","speciality":"","qty":29.0}]},{"drug":"SENNA - LAXAL12 MG TABLET -TRD","patients":3,"qty":110.0,"mrns":["4307","58598","263437"],"avg":36.67,"patientRows":[{"mrn":"4307","name":"ZAHRA SALEH AHMED ALSALAM","speciality":"","qty":36.67},{"mrn":"58598","name":"HUSSAH ZAHER BN ALI ALKHURDAWI","speciality":"","qty":36.67},{"mrn":"263437","name":"YAQEN MOHAMMED ABDALLA ALSAFWINEE","speciality":"","qty":36.67}]},{"drug":"METHOTREXATE - RUXAAR (SPC) 2.5 MG TABLET -TRD","patients":4,"qty":108.0,"mrns":["220266","5913","37270","25328"],"avg":27.0,"patientRows":[{"mrn":"220266","name":"EIMAN TAHA H ALFARAJ","speciality":"","qty":27.0},{"mrn":"5913","name":"NAGYA ALI HUSEN ALHAKIM","speciality":"","qty":27.0},{"mrn":"37270","name":"NADIA MAHDI HABEB SALEEM","speciality":"","qty":27.0},{"mrn":"25328","name":"AFAF AHMAD SALEH AL ALI","speciality":"","qty":27.0}]},{"drug":"EMPAGLIFLOZIN-JARDIANCE 10 MG F.C TABLET -TRD","patients":3,"qty":90.0,"mrns":["292625","143411","80730"],"avg":30.0,"patientRows":[{"mrn":"292625","name":"MOUSA HASSAN MOUSA AL HAMMAD","speciality":"","qty":30.0},{"mrn":"143411","name":"MONEER MOHAMMED H ALZAHER","speciality":"","qty":30.0},{"mrn":"80730","name":"MARIAM ALI MOHAMMAD ALKAAIBI","speciality":"","qty":30.0}]},{"drug":"ROSUVASTATIN - IVARIN 10 MG F.C TABLET -TRD","patients":3,"qty":90.0,"mrns":["543833","4307","674829"],"avg":30.0,"patientRows":[{"mrn":"543833","name":"TAHER AHMED ABDULMOHSEN AL NAMER","speciality":"","qty":30.0},{"mrn":"4307","name":"ZAHRA SALEH AHMED ALSALAM","speciality":"","qty":30.0},{"mrn":"674829","name":"NADA ALAWI H ALHASHIM","speciality":"","qty":30.0}]},{"drug":"VITAMIN B COMPLEX  - TRIPLEX B 100 MG, 200 MG, 200 MCG TABLET -TRD","patients":2,"qty":90.0,"mrns":["400731","19259"],"avg":45.0,"patientRows":[{"mrn":"400731","name":"FATMA FAYEZ HUSEN AL SHHRANY","speciality":"","qty":45.0},{"mrn":"19259","name":"ANWAR KHALED BN AHMAD AL ASFAIR","speciality":"","qty":45.0}]},{"drug":"FINERENONE - KERENDIA 10 MG F.C. TABLET -TRD","patients":2,"qty":88.0,"mrns":["754739","169014"],"avg":44.0,"patientRows":[{"mrn":"754739","name":"MOHAMMED HASSAN H ALHAKIM","speciality":"","qty":44.0},{"mrn":"169014","name":"NAJMA SALEH M ALJARAD","speciality":"","qty":44.0}]},{"drug":"SOMATROPIN - OMNITROPE  5MG/1.5ML CARTRIDGE -TRD","patients":4,"qty":81.0,"mrns":["479954","484486","595132","764415"],"avg":20.25,"patientRows":[{"mrn":"479954","name":"FATIMAH HOSSAM A ALBANNAI","speciality":"","qty":20.25},{"mrn":"484486","name":"YOUSEF JASSEM IBRAHIM HBARAH","speciality":"","qty":20.25},{"mrn":"595132","name":"MAHDY MOHAMMED GAFAR ALREBIH","speciality":"","qty":20.25},{"mrn":"764415","name":"RAWAN AWAD KHALID ALAWAD","speciality":"","qty":20.25}]},{"drug":"CHOLECALCIFEROL; VITAMIN D3- D-SEUL 5,000 UNIT CAPSULE -TRD","patients":9,"qty":75.0,"mrns":["295360","680590","198028","400731","46179","19259","85314","207856","310651"],"avg":8.33,"patientRows":[{"mrn":"295360","name":"GHADAH MAKKI AHMED AL RAMADAN","speciality":"","qty":8.33},{"mrn":"680590","name":"MADINAH MANSOUR ABDALLA KALW","speciality":"","qty":8.33},{"mrn":"198028","name":"ALI MOHAMMAD SALEH ALSHERYAWE","speciality":"","qty":8.33},{"mrn":"400731","name":"FATMA FAYEZ HUSEN AL SHHRANY","speciality":"","qty":8.33},{"mrn":"46179","name":"SAEEDAH AHMED BIN MOHAMMED ALFARAG","speciality":"","qty":8.33},{"mrn":"19259","name":"ANWAR KHALED BN AHMAD AL ASFAIR","speciality":"","qty":8.33},{"mrn":"85314","name":"ALI HASSAN A ALBASRI","speciality":"","qty":8.33},{"mrn":"207856","name":"SHARAF ALAWI BIN RADHI AL KHADHRAWI","speciality":"","qty":8.33},{"mrn":"310651","name":"HESSA AMER LAYL ALKHALDI","speciality":"","qty":8.33}]},{"drug":"SpironoLACtone  -NORACTONE-25 MG TABLET","patients":2,"qty":75.0,"mrns":["275220","429955"],"avg":37.5,"patientRows":[{"mrn":"275220","name":"HUSSAIN ALI BIN ABDULLAH ALMARHOON","speciality":"","qty":37.5},{"mrn":"429955","name":"MAHDY SALEH ABDALLA ALMADEH","speciality":"","qty":37.5}]},{"drug":"DULoxetine - MODEXA 60 MG CAPSULE -TRD","patients":2,"qty":60.0,"mrns":["123101","227365"],"avg":30.0,"patientRows":[{"mrn":"123101","name":"ZAKIAH MOHAMMED K ALRADHI","speciality":"","qty":30.0},{"mrn":"227365","name":"BASMA MOHSEN HABEB AL MUBARAK","speciality":"","qty":30.0}]},{"drug":"EZETIMIBE - ZETEX 10 MG TABLET  -TRD","patients":2,"qty":60.0,"mrns":["292408","143530"],"avg":30.0,"patientRows":[{"mrn":"292408","name":"ALI ABDRABALRASOUL AHMD ALHAMDAN","speciality":"","qty":30.0},{"mrn":"143530","name":"SADIQAH AHMED A AL NAJI","speciality":"","qty":30.0}]},{"drug":"MONTELUKAST-AIRFAST 4 MG SACHET -TRD","patients":2,"qty":60.0,"mrns":["750376","812809"],"avg":30.0,"patientRows":[{"mrn":"750376","name":"DER SALAH MANSOUR NASS","speciality":"","qty":30.0},{"mrn":"812809","name":"FARIS ABDULAZIZ HABUB ALSAYG","speciality":"","qty":30.0}]},{"drug":"PERINDOPRIL-CENORIL-10 MG TAB (COAT)","patients":2,"qty":60.0,"mrns":["299643","250374"],"avg":30.0,"patientRows":[{"mrn":"299643","name":"MASOUMAH AHMED ABDALLA ALJUMAEI","speciality":"","qty":30.0},{"mrn":"250374","name":"ZAHRA SALEH HUSEN ALSAFFAR","speciality":"","qty":30.0}]},{"drug":"POLYETHYLENE GLYCOL -  MOVICOL POWDER SACHET -TRD","patients":2,"qty":60.0,"mrns":["58598","845960"],"avg":30.0,"patientRows":[{"mrn":"58598","name":"HUSSAH ZAHER BN ALI ALKHURDAWI","speciality":"","qty":30.0},{"mrn":"845960","name":"RAMETE KURIKURA  WAKERA","speciality":"","qty":30.0}]},{"drug":"SPIRONOLACTONE - NORACTONE 25 MG TABLET -TRD","patients":2,"qty":60.0,"mrns":["80730","354036"],"avg":30.0,"patientRows":[{"mrn":"80730","name":"MARIAM ALI MOHAMMAD ALKAAIBI","speciality":"","qty":30.0},{"mrn":"354036","name":"ZAKI BIN SAEED AHMED ALQASSAB","speciality":"","qty":30.0}]},{"drug":"VITAMIN B COMPLEX - NEUROVIT 250 MCG,100MG ,250 MG TABLET BOX30 -TRD","patients":2,"qty":60.0,"mrns":["187515","543833"],"avg":30.0,"patientRows":[{"mrn":"187515","name":"ZAHRA SALEH MOHAMMED ALABDULAL","speciality":"","qty":30.0},{"mrn":"543833","name":"TAHER AHMED ABDULMOHSEN AL NAMER","speciality":"","qty":30.0}]},{"drug":"APIXABAN - XCARD 2.5 MG F.C TABLET -TRD","patients":1,"qty":60.0,"mrns":["4307"],"avg":60.0,"patientRows":[{"mrn":"4307","name":"ZAHRA SALEH AHMED ALSALAM","speciality":"","qty":60.0}]},{"drug":"ATORVASTATIN-ATORVA-40 MG TAB","patients":1,"qty":60.0,"mrns":["143530"],"avg":60.0,"patientRows":[{"mrn":"143530","name":"SADIQAH AHMED A AL NAJI","speciality":"","qty":60.0}]},{"drug":"COLCHICINE - ELNASER 500 MCG TABLET -TRD","patients":1,"qty":60.0,"mrns":["205741"],"avg":60.0,"patientRows":[{"mrn":"205741","name":"ZAINAB MAHDI ABDULLAH AL KHALIL","speciality":"","qty":60.0}]},{"drug":"DYDROGESTERONE - DUPHASTON 10 MG F.C TABLET -TRD","patients":1,"qty":60.0,"mrns":["500558"],"avg":60.0,"patientRows":[{"mrn":"500558","name":"SARA MOAED IBRAHIM AL KARAM","speciality":"","qty":60.0}]},{"drug":"ENOXAPARIN - ENDOSA 80 MG/0.8 ML PRE-FILLED SYRINGE -TRD","patients":1,"qty":60.0,"mrns":["140669"],"avg":60.0,"patientRows":[{"mrn":"140669","name":"SHOWQI JASSIM ABDULLAH SHUWAIKHAT","speciality":"","qty":60.0}]},{"drug":"HYDROXYCHLOROQUINE - PLAQUENIL 200 MG F.C TABLET -TRD","patients":1,"qty":60.0,"mrns":["305911"],"avg":60.0,"patientRows":[{"mrn":"305911","name":"ZAHRA ALI ABDALLA AL THONAIAN","speciality":"","qty":60.0}]},{"drug":"METHYLDOPA - ALDOMET 250 MG TABLET -TRD","patients":1,"qty":60.0,"mrns":["169014"],"avg":60.0,"patientRows":[{"mrn":"169014","name":"NAJMA SALEH M ALJARAD","speciality":"","qty":60.0}]},{"drug":"TRIMETAZIDINE (MR) - VASTAREL 35 MG F.C. TABLET -TRD","patients":1,"qty":60.0,"mrns":["129229"],"avg":60.0,"patientRows":[{"mrn":"129229","name":"ABDULHAKEEM ESSA REDHEY ALSHAMMASI","speciality":"","qty":60.0}]},{"drug":"URSODEOXYCHOLIC ACID - URSOFALK 250 MG CAPSULE -TRD","patients":1,"qty":60.0,"mrns":["607308"],"avg":60.0,"patientRows":[{"mrn":"607308","name":"FATIMAH MOHAMMED SAEED ALAWOA","speciality":"","qty":60.0}]},{"drug":"carBAMazepine - TEGretol 400 MG CONTROL RELEASE TABLET -TRD","patients":1,"qty":60.0,"mrns":["587789"],"avg":60.0,"patientRows":[{"mrn":"587789","name":"ZAINAB JAFAR SALEH AMBEREEK","speciality":"","qty":60.0}]},{"drug":"gliCLAzide - DIAOPTIM 60 MG MR TABLET -TRD","patients":1,"qty":60.0,"mrns":["125153"],"avg":60.0,"patientRows":[{"mrn":"125153","name":"HASSAN SALEH HASSAN Alqryr","speciality":"","qty":60.0}]},{"drug":"lamoTRIgine - LAMOTRIX 100  MG TABLET -TRD","patients":1,"qty":60.0,"mrns":["253914"],"avg":60.0,"patientRows":[{"mrn":"253914","name":"ZAINAB HUSSAIN SALEH Al mrabit","speciality":"","qty":60.0}]},{"drug":"lamoTRIgine - LOXOL 25 MG TABLET -TRD","patients":1,"qty":60.0,"mrns":["587789"],"avg":60.0,"patientRows":[{"mrn":"587789","name":"ZAINAB JAFAR SALEH AMBEREEK","speciality":"","qty":60.0}]},{"drug":"lamoTRIgine - LOXOL 50 MG TABLET -TRD","patients":1,"qty":60.0,"mrns":["253914"],"avg":60.0,"patientRows":[{"mrn":"253914","name":"ZAINAB HUSSAIN SALEH Al mrabit","speciality":"","qty":60.0}]},{"drug":"levETIRAcetam - EPITAM 500 MG F.C TABLET -TRD","patients":1,"qty":60.0,"mrns":["146474"],"avg":60.0,"patientRows":[{"mrn":"146474","name":"AQEEL ALI AHMED AL ABDRABALREDA","speciality":"","qty":60.0}]},{"drug":"SACUBITRIL; VALSARTAN - ENTRESTO 200 MG F.C TABLET -TRD","patients":1,"qty":56.0,"mrns":["292408"],"avg":56.0,"patientRows":[{"mrn":"292408","name":"ALI ABDRABALRASOUL AHMD ALHAMDAN","speciality":"","qty":56.0}]},{"drug":"CHOLECALCIFEROL; VITAMIN D3- D-SEUL 10,000 UNIT CAPSULE -TRD","patients":9,"qty":55.0,"mrns":["671240","220266","735217","626181","474815","129057","716501","25328","493845"],"avg":6.11,"patientRows":[{"mrn":"671240","name":"FATIMAH AHMED ABDALLA ALMDARHM","speciality":"","qty":6.11},{"mrn":"220266","name":"EIMAN TAHA H ALFARAJ","speciality":"","qty":6.11},{"mrn":"735217","name":"LAILA ALI BIN RADHI ALALWAN","speciality":"","qty":6.11},{"mrn":"626181","name":"FARAH NADER MUBARAK ALAZMI","speciality":"","qty":6.11},{"mrn":"474815","name":"SUNDUS MOHAMMED ABDULLAH ALQUDAIHI","speciality":"","qty":6.11},{"mrn":"129057","name":"MASOUMAH SALMAN IBRAHIM ALMARHOON","speciality":"","qty":6.11},{"mrn":"716501","name":"SHARIFAH KHALID HUSSAIN ALSHAMMARI","speciality":"","qty":6.11},{"mrn":"25328","name":"AFAF AHMAD SALEH AL ALI","speciality":"","qty":6.11},{"mrn":"493845","name":"MALEEHAH SALMAN GABAL GABAL","speciality":"","qty":6.11}]},{"drug":"PATIROMER-VELTASSA-16.8 Gram SACHET","patients":3,"qty":53.0,"mrns":["27028","4307","169014"],"avg":17.67,"patientRows":[{"mrn":"27028","name":"BILQIS HABIB SALEH ALKHAMIS","speciality":"","qty":17.67},{"mrn":"4307","name":"ZAHRA SALEH AHMED ALSALAM","speciality":"","qty":17.67},{"mrn":"169014","name":"NAJMA SALEH M ALJARAD","speciality":"","qty":17.67}]},{"drug":"ENOXAPARIN - ENDOSA 60 MG/0.6 ML PRE-FILLED SYRINGE -TRD","patients":1,"qty":45.0,"mrns":["716501"],"avg":45.0,"patientRows":[{"mrn":"716501","name":"SHARIFAH KHALID HUSSAIN ALSHAMMARI","speciality":"","qty":45.0}]},{"drug":"Omeprazole- LOSEC MUPS 10 MG TAB","patients":1,"qty":45.0,"mrns":["719210"],"avg":45.0,"patientRows":[{"mrn":"719210","name":"MISK MUSTAFA QASSIM ALDAOOD","speciality":"","qty":45.0}]},{"drug":"METHOTREXATE - EBEWE PHARMA 2.5 MG TABLET -TRD","patients":2,"qty":42.0,"mrns":["46179","202433"],"avg":21.0,"patientRows":[{"mrn":"46179","name":"SAEEDAH AHMED BIN MOHAMMED ALFARAG","speciality":"","qty":21.0},{"mrn":"202433","name":"AMEL MOHMMED EISA ALSAIHATI","speciality":"","qty":21.0}]},{"drug":"INTERFERON BETA-1B - BETAFERON 250 MCG/ML VIAL -TRD","patients":2,"qty":30.0,"mrns":["679656","194190"],"avg":15.0,"patientRows":[{"mrn":"679656","name":"HUSEN IBRAHIM NOUH SHAMIA","speciality":"","qty":15.0},{"mrn":"194190","name":"MADINAH ALI MOHAMMED ELMOHSAN","speciality":"","qty":15.0}]},{"drug":"bisOPROLOL-CARDICOR 5 MG F.C. TABLET -TRD","patients":2,"qty":30.0,"mrns":["73037","80730"],"avg":15.0,"patientRows":[{"mrn":"73037","name":"AHMED SAUD SOLIMAN AL HAJHOOJ","speciality":"","qty":15.0},{"mrn":"80730","name":"MARIAM ALI MOHAMMAD ALKAAIBI","speciality":"","qty":15.0}]},{"drug":"ALLOPURINOL - NO-URIC 100 MG TABLET  -TRD","patients":1,"qty":30.0,"mrns":["744382"],"avg":30.0,"patientRows":[{"mrn":"744382","name":"KHATUN QAZEM YOSEF ALALAWI","speciality":"","qty":30.0}]},{"drug":"ATORVASTATIN - ATORVA 40 MG F.C TABLET - BOX 110 -TRD","patients":1,"qty":30.0,"mrns":["4307"],"avg":30.0,"patientRows":[{"mrn":"4307","name":"ZAHRA SALEH AHMED ALSALAM","speciality":"","qty":30.0}]},{"drug":"CLOPIDOGREL-CLOGREL 75 MG TABLET -TRD","patients":1,"qty":30.0,"mrns":["439017"],"avg":30.0,"patientRows":[{"mrn":"439017","name":"TWAH ABDRBALHUSSAIN H ABU SHLWAH","speciality":"","qty":30.0}]},{"drug":"DIENOGEST - VISANNE  2 MG TABLET -TRD","patients":1,"qty":30.0,"mrns":["265940"],"avg":30.0,"patientRows":[{"mrn":"265940","name":"ALAWIYYAH BAQI BAQER AL MOQBEL","speciality":"","qty":30.0}]},{"drug":"DOMPERIDONE-DOMPY 10 MG TABLET -TRD","patients":1,"qty":30.0,"mrns":["125153"],"avg":30.0,"patientRows":[{"mrn":"125153","name":"HASSAN SALEH HASSAN Alqryr","speciality":"","qty":30.0}]},{"drug":"EMPAGLIFLOZIN-SPC-10 MG F.C TABLET -TRD","patients":1,"qty":30.0,"mrns":["38868"],"avg":30.0,"patientRows":[{"mrn":"38868","name":"LOLO RADI S ALBASHRAWI","speciality":"","qty":30.0}]},{"drug":"EMPAGLIFLOZIN-SPC-25 MG F.C TABLET -TRD","patients":1,"qty":30.0,"mrns":["40859"],"avg":30.0,"patientRows":[{"mrn":"40859","name":"ALI HASSAN YOSEF ALJANABI","speciality":"","qty":30.0}]},{"drug":"FINASTERIDE - FINISCAR 5 MG F.C. TABLET -TRD","patients":1,"qty":30.0,"mrns":["226933"],"avg":30.0,"patientRows":[{"mrn":"226933","name":"MAHDI ESSA R AL AAMAIR","speciality":"","qty":30.0}]},{"drug":"GLIMEPIRIDE - AMAGLIME 2 MG TABLET -TRD","patients":1,"qty":30.0,"mrns":["479459"],"avg":30.0,"patientRows":[{"mrn":"479459","name":"FATMA AHMED RADI ALOLGOM","speciality":"","qty":30.0}]},{"drug":"HYDROXYUREA - CUREAML 500 MG CAPSULE -TRD","patients":1,"qty":30.0,"mrns":["4307"],"avg":30.0,"patientRows":[{"mrn":"4307","name":"ZAHRA SALEH AHMED ALSALAM","speciality":"","qty":30.0}]},{"drug":"LEVOTHYROXINE - EUTHYROX 25 MCG TABLET -TRD","patients":1,"qty":30.0,"mrns":["36374"],"avg":30.0,"patientRows":[{"mrn":"36374","name":"ALI AHMAD ALI ALTLALWAH","speciality":"","qty":30.0}]},{"drug":"LINAGLIPTIN - TRAJENTA 5 MG F.C TABLET -TRD","patients":1,"qty":30.0,"mrns":["429955"],"avg":30.0,"patientRows":[{"mrn":"429955","name":"MAHDY SALEH ABDALLA ALMADEH","speciality":"","qty":30.0}]},{"drug":"MONTELUKAST-LEUKAIR 10 MG F.C. TABLET -TRD","patients":1,"qty":30.0,"mrns":["606246"],"avg":30.0,"patientRows":[{"mrn":"606246","name":"ZAHRA HASSAN M AL MUBARAK","speciality":"","qty":30.0}]},{"drug":"NIFEdipine - INGENUS 60 MG TABLET -TRD","patients":1,"qty":30.0,"mrns":["716501"],"avg":30.0,"patientRows":[{"mrn":"716501","name":"SHARIFAH KHALID HUSSAIN ALSHAMMARI","speciality":"","qty":30.0}]},{"drug":"SITagliptin-JULEEN-100 MG TAB (COAT)","patients":1,"qty":30.0,"mrns":["67986"],"avg":30.0,"patientRows":[{"mrn":"67986","name":"MOHAMMADHASSAN REDHEY SALMAN ALBYABI","speciality":"","qty":30.0}]},{"drug":"SULPIRIDE - DOGMATIL 50 MG CAPSULE -TRD","patients":1,"qty":30.0,"mrns":["293999"],"avg":30.0,"patientRows":[{"mrn":"293999","name":"NARJES HASSAN ALI MOHAMADALI AL HAMADA","speciality":"","qty":30.0}]},{"drug":"TELMISARTAN - NIZORTAN 80 MG TABLET -TRD","patients":1,"qty":30.0,"mrns":["754739"],"avg":30.0,"patientRows":[{"mrn":"754739","name":"MOHAMMED HASSAN H ALHAKIM","speciality":"","qty":30.0}]},{"drug":"amLODIPine- LODIPAM 10 MG F.C TABLET -TRD","patients":1,"qty":30.0,"mrns":["250374"],"avg":30.0,"patientRows":[{"mrn":"250374","name":"ZAHRA SALEH HUSEN ALSAFFAR","speciality":"","qty":30.0}]},{"drug":"hydroCHLOROthiazide - ESIDREX 25 MG TABLET -TRD","patients":1,"qty":30.0,"mrns":["140669"],"avg":30.0,"patientRows":[{"mrn":"140669","name":"SHOWQI JASSIM ABDULLAH SHUWAIKHAT","speciality":"","qty":30.0}]},{"drug":"levoTHYROxine-ELTROXIN-50 MCG TAB","patients":1,"qty":30.0,"mrns":["52001"],"avg":30.0,"patientRows":[{"mrn":"52001","name":"MASUMAH YOUSEF REDHEY ALHELAIL","speciality":"","qty":30.0}]},{"drug":"metFORMIN XR - GLUCARE XR 750 MG TABLET -TRD","patients":1,"qty":30.0,"mrns":["682876"],"avg":30.0,"patientRows":[{"mrn":"682876","name":"RAHMAH MAHDI SALMAN ALBANDARI","speciality":"","qty":30.0}]},{"drug":"DULoxetine - MODEXA 30 MG CAPSULE MR -TRD","patients":1,"qty":28.0,"mrns":["767642"],"avg":28.0,"patientRows":[{"mrn":"767642","name":"DLAYAL HABEB SOUD ALKHALDI","speciality":"","qty":28.0}]},{"drug":"FINASTERIDE-FINISCAR-5 MG TAB","patients":1,"qty":28.0,"mrns":["250245"],"avg":28.0,"patientRows":[{"mrn":"250245","name":"MOHAMMED ALI H AL ASWAD","speciality":"","qty":28.0}]},{"drug":"INSULIN ASPART - novoRAPID100 UNIT/ML IN 3ML FLEXPEN -TRD","patients":7,"qty":27.0,"mrns":["652165","626181","299643","670327","725751","169014","486646"],"avg":3.86,"patientRows":[{"mrn":"652165","name":"JOUD FAHHAD DHAIDAN ALHETHLAN","speciality":"","qty":3.86},{"mrn":"626181","name":"FARAH NADER MUBARAK ALAZMI","speciality":"","qty":3.86},{"mrn":"299643","name":"MASOUMAH AHMED ABDALLA ALJUMAEI","speciality":"","qty":3.86},{"mrn":"670327","name":"DANIEL BASEM ALI ALJABRAN","speciality":"","qty":3.86},{"mrn":"725751","name":"REEM BADER TURKI ALKHALDI","speciality":"","qty":3.86},{"mrn":"169014","name":"NAJMA SALEH M ALJARAD","speciality":"","qty":3.86},{"mrn":"486646","name":"KHWTHER MOHAMMAD KHAMIS ALTAWEEL","speciality":"","qty":3.86}]},{"drug":"POLYETHYLENE GLYCOL; PROPYLENE GLYCOL - SYSTANE- 0.4% /0.3% EYE DROPS -TRD","patients":13,"qty":23.0,"mrns":["727179","308368","52001","457745","596375","599859","797667","292295","105886","603203","763776","814122","305911"],"avg":1.77,"patientRows":[{"mrn":"727179","name":"ZAHRA AHMED MAGED ALSAWAD","speciality":"","qty":1.77},{"mrn":"308368","name":"WAFA ABDULLAH TAQI ALJAROUDI","speciality":"","qty":1.77},{"mrn":"52001","name":"MASUMAH YOUSEF REDHEY ALHELAIL","speciality":"","qty":1.77},{"mrn":"457745","name":"SALEH ABDULLAH M AL DRWISH","speciality":"","qty":1.77},{"mrn":"596375","name":"MOHAMMED KHALED ABDALLA ALHAYAK","speciality":"","qty":1.77},{"mrn":"599859","name":"JAFAR AHMAD ABDALLA ALKHATER","speciality":"","qty":1.77},{"mrn":"797667","name":"EBTISAM HABIB H ALSAIHATI","speciality":"","qty":1.77},{"mrn":"292295","name":"RAMLA HASSAN A MALALAH","speciality":"","qty":1.77},{"mrn":"105886","name":"LAILA SALEH HASSAN AL DUHAYM","speciality":"","qty":1.77},{"mrn":"603203","name":"BUSHRA HUSSAIN A AL MEZAL","speciality":"","qty":1.77},{"mrn":"763776","name":"REEM EISS ABDULLAH AL ABNDI","speciality":"","qty":1.77},{"mrn":"814122","name":"JAWAD ZAKI MANSOUR ALZAYER","speciality":"","qty":1.77},{"mrn":"305911","name":"ZAHRA ALI ABDALLA AL THONAIAN","speciality":"","qty":1.77}]},{"drug":"CARBOMER (POLYACRYLIC ACID) - ARTELAC NIGHT TIME 0.2 % EYE GEL -TRD","patients":13,"qty":21.0,"mrns":["474014","39455","82584","52001","10748","289849","609926","815928","803853","845855","22447","47744","698512"],"avg":1.62,"patientRows":[{"mrn":"474014","name":"ALAA ABDULHADY A ALMOMIN","speciality":"","qty":1.62},{"mrn":"39455","name":"ALI SAEED A ALSHALA","speciality":"","qty":1.62},{"mrn":"82584","name":"MASOUMAH ABDULLAH ABDALLA ALBANDARI","speciality":"","qty":1.62},{"mrn":"52001","name":"MASUMAH YOUSEF REDHEY ALHELAIL","speciality":"","qty":1.62},{"mrn":"10748","name":"AHMAD SAEED ABDULMOHSIN AL GHURAB","speciality":"","qty":1.62},{"mrn":"289849","name":"AFRAH MANSOUR ABDULAH ALHIRZ","speciality":"","qty":1.62},{"mrn":"609926","name":"NAJAH ABDULLAH HUSEN AL BORI","speciality":"","qty":1.62},{"mrn":"815928","name":"MOUSA MOHAMMED MOUSA ALMOMEN","speciality":"","qty":1.62},{"mrn":"803853","name":"NAJLA ABDULRAZAQ AHMED ALGHAREEB","speciality":"","qty":1.62},{"mrn":"845855","name":"HASSAN ALI H ALHAIKI","speciality":"","qty":1.62},{"mrn":"22447","name":"ZAHRA ABDULLAH H ALORAYEDH","speciality":"","qty":1.62},{"mrn":"47744","name":"IBTIHAL SALMAN AHMAD DARWEESH","speciality":"","qty":1.62},{"mrn":"698512","name":"SAEED SAEED HUSSEIN SALEH","speciality":"","qty":1.62}]},{"drug":"DICLOFENAC - AVOTRENE 1% IN 100 G TUBE -TRD","patients":14,"qty":20.0,"mrns":["718589","11974","41318","777279","44431","13632","445259","474896","88851","59801","221881","462186","717215","844610"],"avg":1.43,"patientRows":[{"mrn":"718589","name":"AWATEF IBRAHIM AHMED ALGHAFLI","speciality":"","qty":1.43},{"mrn":"11974","name":"AMIRAH ALI SALMAN ALHAMALY","speciality":"","qty":1.43},{"mrn":"41318","name":"MASOUMAH IBRAHIM Y ALJAROODI","speciality":"","qty":1.43},{"mrn":"777279","name":"FATEMAH FARHAN ABDALLA ALSUFYANI","speciality":"","qty":1.43},{"mrn":"44431","name":"MASOUMA ABDULLAH A ALMAHROOS","speciality":"","qty":1.43},{"mrn":"13632","name":"MALIHA ABBAS HASHIM ALSHAKHOORI","speciality":"","qty":1.43},{"mrn":"445259","name":"HUSSAIN HASSAN HASHEM ALQASSAB","speciality":"","qty":1.43},{"mrn":"474896","name":"HABEB ABD EL MEGED ADB EL MOHASSEN ALZAKI","speciality":"","qty":1.43},{"mrn":"88851","name":"MONA ABDULKAREEM M AL KHATER","speciality":"","qty":1.43},{"mrn":"59801","name":"HUSSAIN ABDRABALRASOOL YOSEF AL HAJJI","speciality":"","qty":1.43},{"mrn":"221881","name":"ZAINAB ALI I AL MBEREEK","speciality":"","qty":1.43},{"mrn":"462186","name":"FATEMAH MOHAMMED A Al dawad","speciality":"","qty":1.43},{"mrn":"717215","name":"NAEMA ALI SALEH ALHAMAL","speciality":"","qty":1.43},{"mrn":"844610","name":"ZEESHAN   HAIDER","speciality":"","qty":1.43}]},{"drug":"NAPROXEN - NAPROX 250 MG F.C TABLET -TRD","patients":1,"qty":20.0,"mrns":["439017"],"avg":20.0,"patientRows":[{"mrn":"439017","name":"TWAH ABDRBALHUSSAIN H ABU SHLWAH","speciality":"","qty":20.0}]},{"drug":"SALBUTAMOL - BUTALIN  100 MCG INHALER -TRD","patients":13,"qty":19.0,"mrns":["222220","417650","743510","165412","12179","777279","804315","671288","14387","750376","828629","836803","812809"],"avg":1.46,"patientRows":[{"mrn":"222220","name":"HUDA ALI ABDALLA AL SALEM","speciality":"","qty":1.46},{"mrn":"417650","name":"SALEH KHALEFAH A ALHASAWI","speciality":"","qty":1.46},{"mrn":"743510","name":"MALAK BADER MANSSOR ALSADEER","speciality":"","qty":1.46},{"mrn":"165412","name":"ZAHRA REDHEY JAWAD ALQUNIZI","speciality":"","qty":1.46},{"mrn":"12179","name":"LAILA SAEED ABDALLA ALKHALAF","speciality":"","qty":1.46},{"mrn":"777279","name":"FATEMAH FARHAN ABDALLA ALSUFYANI","speciality":"","qty":1.46},{"mrn":"804315","name":"WARD SALIH MAHDI AL SALMAN","speciality":"","qty":1.46},{"mrn":"671288","name":"FATIMAH SALEH A ALMOMEN","speciality":"","qty":1.46},{"mrn":"14387","name":"HUSEN AHMED HUSEN HAMEEDI","speciality":"","qty":1.46},{"mrn":"750376","name":"DER SALAH MANSOUR NASS","speciality":"","qty":1.46},{"mrn":"828629","name":"YOUSEF QASSIM ABDULLAH ALJARAD","speciality":"","qty":1.46},{"mrn":"836803","name":"SARAH QASSIM ABDULLAH ALJARAD","speciality":"","qty":1.46},{"mrn":"812809","name":"FARIS ABDULAZIZ HABUB ALSAYG","speciality":"","qty":1.46}]},{"drug":"MOMETASONE FUROATE-AVOCOM 0.05 % NASAL SPRAY -TRD","patients":13,"qty":16.0,"mrns":["345272","24427","533295","739892","410855","583276","646292","600082","281574","680258","683953","621615","314118"],"avg":1.23,"patientRows":[{"mrn":"345272","name":"FARIDA ALI HABEB al fareid","speciality":"","qty":1.23},{"mrn":"24427","name":"BATUL RADI H ALABED","speciality":"","qty":1.23},{"mrn":"533295","name":"AMNAH IBRAHIM AHMED ALNASHRI","speciality":"","qty":1.23},{"mrn":"739892","name":"HASHIM MOHAMMED HUSSAIN ALBAHRANI","speciality":"","qty":1.23},{"mrn":"410855","name":"AREEJ MOHAMMAD GAFAR AL ALSHAIKH","speciality":"","qty":1.23},{"mrn":"583276","name":"AYAT AHMED M AL MOHSEN","speciality":"","qty":1.23},{"mrn":"646292","name":"MNAHIL SHAMSELDEEN MOHAMED SULIMAN","speciality":"","qty":1.23},{"mrn":"600082","name":"ALI AHMED A ALDARWISH","speciality":"","qty":1.23},{"mrn":"281574","name":"FATIMAH SAUD A AL ALI","speciality":"","qty":1.23},{"mrn":"680258","name":"BAYAN KHALAF QASHMAT ALKHALDI","speciality":"","qty":1.23},{"mrn":"683953","name":"MOHAMMED HASSAN AHMED ALSAYEGH","speciality":"","qty":1.23},{"mrn":"621615","name":"HASSAN KHALIL IBRAHIM MOGHIS","speciality":"","qty":1.23},{"mrn":"314118","name":"ZAINAB MOHAMMAD J KHATEM","speciality":"","qty":1.23}]},{"drug":"bisoPROLOL-CARDICOR-5 MG TAB","patients":1,"qty":15.0,"mrns":["38868"],"avg":15.0,"patientRows":[{"mrn":"38868","name":"LOLO RADI S ALBASHRAWI","speciality":"","qty":15.0}]},{"drug":"DICLOFENAC-AVOTRENE-10 MG/G TUBE","patients":13,"qty":13.0,"mrns":["204602","671288","72885","1124","129057","123330","420885","265443","621541","461073","293298","257344","128850"],"avg":1.0,"patientRows":[{"mrn":"204602","name":"KHADIJAH SALEH QAZEM ALMSABAH","speciality":"","qty":1.0},{"mrn":"671288","name":"FATIMAH SALEH A ALMOMEN","speciality":"","qty":1.0},{"mrn":"72885","name":"FATIMA ALI M ALJANBI","speciality":"","qty":1.0},{"mrn":"1124","name":"SARAH HAMAD MOHAMMED ALKHALDI","speciality":"","qty":1.0},{"mrn":"129057","name":"MASOUMAH SALMAN IBRAHIM ALMARHOON","speciality":"","qty":1.0},{"mrn":"123330","name":"FATIMAH ALI SALMAN AL SHAWAF","speciality":"","qty":1.0},{"mrn":"420885","name":"NABEEL ALI HASSAN ALLEBAD","speciality":"","qty":1.0},{"mrn":"265443","name":"MURTADA SHAKER A AL SADIQ","speciality":"","qty":1.0},{"mrn":"621541","name":"SAAD SAUD S ALKHALDI","speciality":"","qty":1.0},{"mrn":"461073","name":"AFRAH ALI YOSEF ALSHAWIKHAT","speciality":"","qty":1.0},{"mrn":"293298","name":"ZAHRA ABDULLAH ESSA AL SALEM","speciality":"","qty":1.0},{"mrn":"257344","name":"MEHDI SALEH I ALASEEL","speciality":"","qty":1.0},{"mrn":"128850","name":"ZAHRA SALMAN A ALTURAISH","speciality":"","qty":1.0}]},{"drug":"FLUTICASONE-FLUSORT 0.05 % NASAL SPRAY -TRD","patients":6,"qty":12.0,"mrns":["74430","813819","623202","614871","67457","359881"],"avg":2.0,"patientRows":[{"mrn":"74430","name":"FATIMAH FARDAN MOHAMMED AL DARWISH","speciality":"","qty":2.0},{"mrn":"813819","name":"RAHIL KIFAH ALI AL SALAM","speciality":"","qty":2.0},{"mrn":"623202","name":"ABDRABALRASOOL ABDALLA HASSAN AL HAJARI","speciality":"","qty":2.0},{"mrn":"614871","name":"MAHDI ALI HASSAN ALMUTAWAH","speciality":"","qty":2.0},{"mrn":"67457","name":"ABDULLAH HASSAN Abudalla RADWAN","speciality":"","qty":2.0},{"mrn":"359881","name":"SARA MUFEED S ALSINAN","speciality":"","qty":2.0}]},{"drug":"brinZOLamide:TIMOLOL-AZARGA-EYE DROPS 5 MG/ML","patients":6,"qty":12.0,"mrns":["529952","305746","741740","6569","599859","306556"],"avg":2.0,"patientRows":[{"mrn":"529952","name":"SAMAH HASSAN MOHAMMED ALDERAZI","speciality":"","qty":2.0},{"mrn":"305746","name":"FATIMAH ALI MOHAMMED AL YAQUB","speciality":"","qty":2.0},{"mrn":"741740","name":"LAILA AHMED MUSAWI RUBAYYI","speciality":"","qty":2.0},{"mrn":"6569","name":"MONA ALI S ALKHURIDAH","speciality":"","qty":2.0},{"mrn":"599859","name":"JAFAR AHMAD ABDALLA ALKHATER","speciality":"","qty":2.0},{"mrn":"306556","name":"MADINA MOHAMMAD MAHDI ABUZEED","speciality":"","qty":2.0}]},{"drug":"INSULIN DEGLUDEC - TRESIBA FLEXPEN 100 UNIT/ML IN 3MLPENFILL -TRD","patients":4,"qty":12.0,"mrns":["652165","670327","725751","486646"],"avg":3.0,"patientRows":[{"mrn":"652165","name":"JOUD FAHHAD DHAIDAN ALHETHLAN","speciality":"","qty":3.0},{"mrn":"670327","name":"DANIEL BASEM ALI ALJABRAN","speciality":"","qty":3.0},{"mrn":"725751","name":"REEM BADER TURKI ALKHALDI","speciality":"","qty":3.0},{"mrn":"486646","name":"KHWTHER MOHAMMAD KHAMIS ALTAWEEL","speciality":"","qty":3.0}]},{"drug":"ABATACEPT- ORENCIA 125 MG PRE-FILLED SYRINGE  -TRD","patients":3,"qty":12.0,"mrns":["38605","5913","25328"],"avg":4.0,"patientRows":[{"mrn":"38605","name":"HUDA AJEEB SALEH ALHASSAN","speciality":"","qty":4.0},{"mrn":"5913","name":"NAGYA ALI HUSEN ALHAKIM","speciality":"","qty":4.0},{"mrn":"25328","name":"AFAF AHMAD SALEH AL ALI","speciality":"","qty":4.0}]},{"drug":"carBAMazepine - TEGretol 100 MG/5 ML IN 100 Ml BOTTLE -TRD","patients":1,"qty":12.0,"mrns":["701437"],"avg":12.0,"patientRows":[{"mrn":"701437","name":"ZAHRA AHMED ABDALLA AL MOZARAA","speciality":"","qty":12.0}]},{"drug":"TIOTROPIUM - SPIRIVA 18MCG (HARD CAPSULE) INHALER -TRD","patients":8,"qty":8.0,"mrns":["417650","165412","19822","777279","533295","606246","671288","410855"],"avg":1.0,"patientRows":[{"mrn":"417650","name":"SALEH KHALEFAH A ALHASAWI","speciality":"","qty":1.0},{"mrn":"165412","name":"ZAHRA REDHEY JAWAD ALQUNIZI","speciality":"","qty":1.0},{"mrn":"19822","name":"JAMIL ALI M ALTHABET","speciality":"","qty":1.0},{"mrn":"777279","name":"FATEMAH FARHAN ABDALLA ALSUFYANI","speciality":"","qty":1.0},{"mrn":"533295","name":"AMNAH IBRAHIM AHMED ALNASHRI","speciality":"","qty":1.0},{"mrn":"606246","name":"ZAHRA HASSAN M AL MUBARAK","speciality":"","qty":1.0},{"mrn":"671288","name":"FATIMAH SALEH A ALMOMEN","speciality":"","qty":1.0},{"mrn":"410855","name":"AREEJ MOHAMMAD GAFAR AL ALSHAIKH","speciality":"","qty":1.0}]},{"drug":"DORZOLAMIDE; TIMOLOL - XOLAMOL 2%; 0.5% EYE DROPS, 5 ML -TRD","patients":5,"qty":8.0,"mrns":["308368","36197","270442","49080","707562"],"avg":1.6,"patientRows":[{"mrn":"308368","name":"WAFA ABDULLAH TAQI ALJAROUDI","speciality":"","qty":1.6},{"mrn":"36197","name":"ABDULLAH HASSAN ALI LTURAIK","speciality":"","qty":1.6},{"mrn":"270442","name":"ABDULLA NASSER A ALABBAD","speciality":"","qty":1.6},{"mrn":"49080","name":"AFRAA MOHAMMED M ALHAJRI","speciality":"","qty":1.6},{"mrn":"707562","name":"FATIMAH MOHAMMED AHMED ALSURAIH","speciality":"","qty":1.6}]},{"drug":"INSULIN GLARGINE - LANTUS SOLOSTAR 300 UNIT/3ML PEE-FILLED PEN -TRD","patients":5,"qty":8.0,"mrns":["67986","462235","626181","429955","140669"],"avg":1.6,"patientRows":[{"mrn":"67986","name":"MOHAMMADHASSAN REDHEY SALMAN ALBYABI","speciality":"","qty":1.6},{"mrn":"462235","name":"AFIFAH ALI MOBARK ALJESHI","speciality":"","qty":1.6},{"mrn":"626181","name":"FARAH NADER MUBARAK ALAZMI","speciality":"","qty":1.6},{"mrn":"429955","name":"MAHDY SALEH ABDALLA ALMADEH","speciality":"","qty":1.6},{"mrn":"140669","name":"SHOWQI JASSIM ABDULLAH SHUWAIKHAT","speciality":"","qty":1.6}]},{"drug":"EVOLOCUMAB - REPATHA  140 MG/1 ML PRE-FILLED PEN  -TRD","patients":4,"qty":8.0,"mrns":["531254","143530","12844","505746"],"avg":2.0,"patientRows":[{"mrn":"531254","name":"ALI ABDALLA ALI ALSINAN","speciality":"","qty":2.0},{"mrn":"143530","name":"SADIQAH AHMED A AL NAJI","speciality":"","qty":2.0},{"mrn":"12844","name":"SADIQ ABDULLAH KATHEM AL SAHWAN","speciality":"","qty":2.0},{"mrn":"505746","name":"MOUSA IBRAHIM H AL DHAHI","speciality":"","qty":2.0}]},{"drug":"DARBEPOETIN ALFA- ARANESP 40 MCG/0.4 ML PRE-FILLED SYRINGE -TRD","patients":2,"qty":8.0,"mrns":["618549","480035"],"avg":4.0,"patientRows":[{"mrn":"618549","name":"TAHANI ALI HASSAN ALDAGAM","speciality":"","qty":4.0},{"mrn":"480035","name":"ABDULLAH ESSA A AL YOUSEF","speciality":"","qty":4.0}]},{"drug":"BUDESONIDE -  CORTRIEF 64 MCG NASAL SPRAY -TRD","patients":5,"qty":5.0,"mrns":["237300","483712","549690","606246","785789"],"avg":1.0,"patientRows":[{"mrn":"237300","name":"ZAKIAH ABDULLAH HUSSAIN AL ARIDH","speciality":"","qty":1.0},{"mrn":"483712","name":"RABAB ABDALLA AHMED ALAJAMI","speciality":"","qty":1.0},{"mrn":"549690","name":"BAYAN HASAN ALI ALEISANI","speciality":"","qty":1.0},{"mrn":"606246","name":"ZAHRA HASSAN M AL MUBARAK","speciality":"","qty":1.0},{"mrn":"785789","name":"MONA ABDULLAH M AL JUBRAN","speciality":"","qty":1.0}]},{"drug":"CHOLECALCIFEROL; VITAMIN D3 - TOPFEROL 50,000 UNIT TABLET -TRD","patients":5,"qty":5.0,"mrns":["38605","187515","194968","4307","80730"],"avg":1.0,"patientRows":[{"mrn":"38605","name":"HUDA AJEEB SALEH ALHASSAN","speciality":"","qty":1.0},{"mrn":"187515","name":"ZAHRA SALEH MOHAMMED ALABDULAL","speciality":"","qty":1.0},{"mrn":"194968","name":"FATIMAH MOHAMMED IBRAHIM ALSAIHATI","speciality":"","qty":1.0},{"mrn":"4307","name":"ZAHRA SALEH AHMED ALSALAM","speciality":"","qty":1.0},{"mrn":"80730","name":"MARIAM ALI MOHAMMAD ALKAAIBI","speciality":"","qty":1.0}]},{"drug":"BIMATOPROST - LUMIGAN 0.1MG/ML EYE DROPS -TRD","patients":3,"qty":5.0,"mrns":["305746","38620","202656"],"avg":1.67,"patientRows":[{"mrn":"305746","name":"FATIMAH ALI MOHAMMED AL YAQUB","speciality":"","qty":1.67},{"mrn":"38620","name":"MADINA ABDULAH AHMAD AL MATOOQ","speciality":"","qty":1.67},{"mrn":"202656","name":"MASOMAH ABDULAH MANSOUR MARHOON","speciality":"","qty":1.67}]},{"drug":"FERROUS SULFATE - FEROMIN 125 MG (25 MG ELEMENTAL IRON)/ML IN 30 ML ORAL DROPS -TRD","patients":2,"qty":5.0,"mrns":["794642","577137"],"avg":2.5,"patientRows":[{"mrn":"794642","name":"LEEN MUFID SALEH ALSHMASI","speciality":"","qty":2.5},{"mrn":"577137","name":"ABDULHADI MANA SAYED ALQAHTANI","speciality":"","qty":2.5}]},{"drug":"FLUTICASONE PROPIONATE - FLIXOTIDE EVOHALER 50 MCG INHALER -TRD","patients":4,"qty":4.0,"mrns":["743510","822303","750376","828629"],"avg":1.0,"patientRows":[{"mrn":"743510","name":"MALAK BADER MANSSOR ALSADEER","speciality":"","qty":1.0},{"mrn":"822303","name":"WARD FOUAD ALWAI ALSADAH","speciality":"","qty":1.0},{"mrn":"750376","name":"DER SALAH MANSOUR NASS","speciality":"","qty":1.0},{"mrn":"828629","name":"YOUSEF QASSIM ABDULLAH ALJARAD","speciality":"","qty":1.0}]},{"drug":"levETIRAcetam - LAVIE 100 MG/ML IN 150 ML BOTTLE -TRD","patients":2,"qty":4.0,"mrns":["723015","702465"],"avg":2.0,"patientRows":[{"mrn":"723015","name":"LUJAIN ABDULELAH HUSSAIN ALZAIN","speciality":"","qty":2.0},{"mrn":"702465","name":"SALMAN HASSAN MOHAMMED ALSHARYAWI","speciality":"","qty":2.0}]},{"drug":"DARBEPOETIN ALFA- ARANESP 80 MCG/0.4 ML PRE-FILLED SYRINGE -TRD","patients":1,"qty":4.0,"mrns":["4307"],"avg":4.0,"patientRows":[{"mrn":"4307","name":"ZAHRA SALEH AHMED ALSALAM","speciality":"","qty":4.0}]},{"drug":"ETANERCEPT - NEPEXTO 50 MG PRE-FILLED PEN -TRD","patients":1,"qty":4.0,"mrns":["295360"],"avg":4.0,"patientRows":[{"mrn":"295360","name":"GHADAH MAKKI AHMED AL RAMADAN","speciality":"","qty":4.0}]},{"drug":"FOLIC ACID-BEFOLVIT-5 MG TAB","patients":1,"qty":4.0,"mrns":["220266"],"avg":4.0,"patientRows":[{"mrn":"220266","name":"EIMAN TAHA H ALFARAJ","speciality":"","qty":4.0}]},{"drug":"FOLIC ACID-FOLICUM- 5 MG TAB","patients":1,"qty":4.0,"mrns":["194968"],"avg":4.0,"patientRows":[{"mrn":"194968","name":"FATIMAH MOHAMMED IBRAHIM ALSAIHATI","speciality":"","qty":4.0}]},{"drug":"INSULIN GLULISINE - APIDRA SOLOSTAR 100 UNIT/1 ML PRE-FILLED PEN  -TRD","patients":1,"qty":4.0,"mrns":["609926"],"avg":4.0,"patientRows":[{"mrn":"609926","name":"NAJAH ABDULLAH HUSEN AL BORI","speciality":"","qty":4.0}]},{"drug":"TIMOLOL - OPTIMOL 0.5% EYE DROP -TRD","patients":1,"qty":4.0,"mrns":["78575"],"avg":4.0,"patientRows":[{"mrn":"78575","name":"RUQAYYAH RAMADAN JAFAR ALMADAN","speciality":"","qty":4.0}]},{"drug":"BUDESONIDE;FORMOTEROL - BUFOMIX 160 MCG; 4.5 MCG/DOSE INHALER -TRD","patients":3,"qty":3.0,"mrns":["237300","270828","606246"],"avg":1.0,"patientRows":[{"mrn":"237300","name":"ZAKIAH ABDULLAH HUSSAIN AL ARIDH","speciality":"","qty":1.0},{"mrn":"270828","name":"AMANI MOHAMMED HUSSAIN AL YAQOUB","speciality":"","qty":1.0},{"mrn":"606246","name":"ZAHRA HASSAN M AL MUBARAK","speciality":"","qty":1.0}]},{"drug":"SODIUM CHLORIDE - NASOCARE 0.9 % NASAL SPRAY -TRD","patients":3,"qty":3.0,"mrns":["97742","725751","836803"],"avg":1.0,"patientRows":[{"mrn":"97742","name":"FAISAL HUSSAIN EISA ALKASSAR","speciality":"","qty":1.0},{"mrn":"725751","name":"REEM BADER TURKI ALKHALDI","speciality":"","qty":1.0},{"mrn":"836803","name":"SARAH QASSIM ABDULLAH ALJARAD","speciality":"","qty":1.0}]},{"drug":"ZINC OXIDE - NAPHOZINC PLUS 15 % CREAM -TRD","patients":1,"qty":3.0,"mrns":["174072"],"avg":3.0,"patientRows":[{"mrn":"174072","name":"ZAHAR MANSOUR HASSAN SELAIS","speciality":"","qty":3.0}]},{"drug":"CALCIUM POLYSTYRENE - ROMACIN 300 G JAR ( POWDER ) -TRD","patients":2,"qty":2.0,"mrns":["169014","48342"],"avg":1.0,"patientRows":[{"mrn":"169014","name":"NAJMA SALEH M ALJARAD","speciality":"","qty":1.0},{"mrn":"48342","name":"FATIMA ALI HUSEN ALKHAWAHER","speciality":"","qty":1.0}]},{"drug":"FLUTICASONE FURATE, VILANTEROL - RELVAR ELLIPTA100 MCG; 25 MCG INHALER -TRD","patients":2,"qty":2.0,"mrns":["38605","671288"],"avg":1.0,"patientRows":[{"mrn":"38605","name":"HUDA AJEEB SALEH ALHASSAN","speciality":"","qty":1.0},{"mrn":"671288","name":"FATIMAH SALEH A ALMOMEN","speciality":"","qty":1.0}]},{"drug":"FLUTICASONE PROPIONATE- FLIXOTIDE - 125 MCG INHALER -TRD","patients":2,"qty":2.0,"mrns":["804315","836803"],"avg":1.0,"patientRows":[{"mrn":"804315","name":"WARD SALIH MAHDI AL SALMAN","speciality":"","qty":1.0},{"mrn":"836803","name":"SARAH QASSIM ABDULLAH ALJARAD","speciality":"","qty":1.0}]},{"drug":"MULTIVITAMINS PEDIA- SANOVIT 160 ML SYRUP -TRD","patients":2,"qty":2.0,"mrns":["824200","680258"],"avg":1.0,"patientRows":[{"mrn":"824200","name":"QAMAR MONER NURI ALSAKHIN","speciality":"","qty":1.0},{"mrn":"680258","name":"BAYAN KHALAF QASHMAT ALKHALDI","speciality":"","qty":1.0}]},{"drug":"TERIPARATIDE-BONTEO 620 MCG/2.48ML PRE-FILLED PEN -TRD","patients":2,"qty":2.0,"mrns":["508335","671240"],"avg":1.0,"patientRows":[{"mrn":"508335","name":"NAIMAH AHMED SALMAN AL REBH","speciality":"","qty":1.0},{"mrn":"671240","name":"FATIMAH AHMED ABDALLA ALMDARHM","speciality":"","qty":1.0}]},{"drug":"ADALIMUMAB - HULIO 40MG/0.8 ML PREFILLED SYRING -TRD","patients":1,"qty":2.0,"mrns":["674829"],"avg":2.0,"patientRows":[{"mrn":"674829","name":"NADA ALAWI H ALHASHIM","speciality":"","qty":2.0}]},{"drug":"B-SITOSTEROL-AVOMEB-0.25%  OINT TUBE.","patients":1,"qty":2.0,"mrns":["462235"],"avg":2.0,"patientRows":[{"mrn":"462235","name":"AFIFAH ALI MOBARK ALJESHI","speciality":"","qty":2.0}]},{"drug":"CERTOLIZUMAB - CIMZIA 200 MG / 1ML PREFILLED SYRING -TRD","patients":1,"qty":2.0,"mrns":["308032"],"avg":2.0,"patientRows":[{"mrn":"308032","name":"SAKINAH ALI ABDELRHEEM ALNASSER","speciality":"","qty":2.0}]},{"drug":"SODIUM HYALURONATE - HYFRESH 2 MG EYE DROPS -TRD","patients":1,"qty":2.0,"mrns":["97742"],"avg":2.0,"patientRows":[{"mrn":"97742","name":"FAISAL HUSSAIN EISA ALKASSAR","speciality":"","qty":2.0}]},{"drug":"TOCILIZUMAB - TYENNE 162 MG/0.9ML PREFILLED SYRING -TRD","patients":1,"qty":2.0,"mrns":["220266"],"avg":2.0,"patientRows":[{"mrn":"220266","name":"EIMAN TAHA H ALFARAJ","speciality":"","qty":2.0}]},{"drug":"ALUMINUM HYDROXIDE; MAGNESIUM HYDROXIDE -  MOXAL 405 MG;100 MG / 5ML  SUSPENSION -TRD","patients":1,"qty":1.0,"mrns":["297760"],"avg":1.0,"patientRows":[{"mrn":"297760","name":"AHMAD IBRAHIM AHMAD AL MOBARAK","speciality":"","qty":1.0}]},{"drug":"BETA-SITOSTEROL - AVOMEB 0.25 MG/ML OINTMENT -TRD","patients":1,"qty":1.0,"mrns":["417650"],"avg":1.0,"patientRows":[{"mrn":"417650","name":"SALEH KHALEFAH A ALHASAWI","speciality":"","qty":1.0}]},{"drug":"FLUTICASONE FURATE, VILANTEROL - RELVAR ELLIPTA 200 MCG/ 25 MCG INHALER -TRD","patients":1,"qty":1.0,"mrns":["12179"],"avg":1.0,"patientRows":[{"mrn":"12179","name":"LAILA SAEED ABDALLA ALKHALAF","speciality":"","qty":1.0}]},{"drug":"GENTAMICIN - APIGEN 0.3% EYE OINTMENT -TRD","patients":1,"qty":1.0,"mrns":["4307"],"avg":1.0,"patientRows":[{"mrn":"4307","name":"ZAHRA SALEH AHMED ALSALAM","speciality":"","qty":1.0}]},{"drug":"LACTULOSE - LAXILOSE 3.35G/5ML IN 300 ML SYRUP -TRD","patients":1,"qty":1.0,"mrns":["680590"],"avg":1.0,"patientRows":[{"mrn":"680590","name":"MADINAH MANSOUR ABDALLA KALW","speciality":"","qty":1.0}]},{"drug":"MOMETASONE FUROATE-TABUNEX 0.05 % NASAL SPRAY -TRD","patients":1,"qty":1.0,"mrns":["706884"],"avg":1.0,"patientRows":[{"mrn":"706884","name":"HAIDAR MOHAMMED ALI ALMUTILAIE","speciality":"","qty":1.0}]},{"drug":"OLOPATADINE - OLOPAT 0.1 % EYE DROPS -TRD","patients":1,"qty":1.0,"mrns":["751980"],"avg":1.0,"patientRows":[{"mrn":"751980","name":"MUZAMMIL ABBAS ALLAH DITTA","speciality":"","qty":1.0}]},{"drug":"SALBUTAMOL - BRONCHOVENT 5 MG/ML BOTTLE NEBULIZER -TRD","patients":1,"qty":1.0,"mrns":["822303"],"avg":1.0,"patientRows":[{"mrn":"822303","name":"WARD FOUAD ALWAI ALSADAH","speciality":"","qty":1.0}]},{"drug":"SEMAGLUTIDE - OZEMPIC 0.5 MG PREFILLED SYRINGE -TRD","patients":1,"qty":1.0,"mrns":["179229"],"avg":1.0,"patientRows":[{"mrn":"179229","name":"HUSSAIN HASSAN A ALKHADRAWI","speciality":"","qty":1.0}]},{"drug":"URSODEOXYCHOLIC ACID - URSOFALK 50 MG/ML N 250 ML SUSPENSION","patients":1,"qty":1.0,"mrns":["835220"],"avg":1.0,"patientRows":[{"mrn":"835220","name":"ZAKARIA MENHAL HASSAN ZAKARIA","speciality":"","qty":1.0}]},{"drug":"USTEKINUMAB - STELARA 90 MG/ML PRE-FILLED SYRINGE -TRD","patients":1,"qty":1.0,"mrns":["386866"],"avg":1.0,"patientRows":[{"mrn":"386866","name":"EMAN AHMED BN HAUSSAN ALFARDAN","speciality":"","qty":1.0}]}]}