{"date":"2026-11-05","rows":[{"drug":"SODIUM CARBOXYMETHYLCELLULOSE:GLYCERINE-OPTIVE UD-0.5%:0.9% MINIMS","patients":30,"qty":1470.0,"mrns":["415215","118065","289795","168099","838891","412375","791350","564744","591002","338255","753097","826824","425422","574127","384780","208586","294455","15830","119903","105092","842369","215455","200043","842739","390653","365412","153321","66438","226338","468651"]},{"drug":"AMLODIPINE-LODIPAM-5 MG TAB (COAT)","patients":9,"qty":420.0,"mrns":["25715","319222","836482","371885","274540","125011","201956","6184","203029"]},{"drug":"Omeprazole-OMERAL-20 MG CAP.","patients":8,"qty":390.0,"mrns":["237991","559755","335603","650030","247930","319222","797673","338308"]},{"drug":"azaTHIOprine -IMURAN 50 MG TABLET -TRD","patients":4,"qty":315.0,"mrns":["50385","25715","749682","385923"]},{"drug":"ESOMEPRAZOLE - ESOPOLE 20 MG CAPSULE -TRD","patients":7,"qty":312.0,"mrns":["634504","264058","749682","153935","458807","26539","188176"]},{"drug":"SODIUM BICARBONATE -NA BICA 325 MG TABLET -TRD","patients":2,"qty":300.0,"mrns":["268444","371885"]},{"drug":"carBAMazepine - CARBATOL 200 MG TABLET-BOX500 -TRD","patients":2,"qty":300.0,"mrns":["234060","241615"]},{"drug":"MESALAZINE - PENTASA 500 MG SLOW-RELEASE TABLET -TRD","patients":3,"qty":270.0,"mrns":["749682","787607","790604"]},{"drug":"CHOLECALCIFEROL; VITAMIN D3-RONZAVIT 1,000 UNIT CAPSULE -TRD","patients":8,"qty":240.0,"mrns":["95655","335603","30882","155836","157244","203840","472667","701989"]},{"drug":"PERINDOPRIL-TENORYL-5 MG TAB","patients":7,"qty":240.0,"mrns":["299031","672236","650030","150735","371885","125011","231019"]},{"drug":"VITAMIN B COMPLEX  - TRIPLEX B 100 MG, 200 MG, 200 MCG TABLET -TRD","patients":4,"qty":240.0,"mrns":["435108","699686","720797","665453"]},{"drug":"PROPRANOLOL - INDICARDIN 10 MG TABLET -TRD","patients":1,"qty":240.0,"mrns":["314528"]},{"drug":"metFORMIN XR - GLUCOPHAGE XR 750 MG TABLET -TRD","patients":4,"qty":210.0,"mrns":["299031","335603","749682","16172"]},{"drug":"TAMSULOSIN - PROSTA 0.4 MG P.R TABLET -TRD","patients":6,"qty":180.0,"mrns":["142065","219236","591832","274540","346286","680671"]},{"drug":"ROSUVASTATIN - IVARIN 10 MG F.C TABLET -TRD","patients":1,"qty":179.0,"mrns":["791193"]},{"drug":"ALFUZOSIN - URITAB XL 10 MG TABLET  -TRD","patients":5,"qty":150.0,"mrns":["523799","639593","122743","39655","184908"]},{"drug":"OMEPRAZOLE - OMERAL 20 MG CAPSULE-BOX100 -TRD","patients":3,"qty":150.0,"mrns":["139369","16172","590624"]},{"drug":"LEVOTHYROXINE - EUTHYROX 25 MCG TABLET -TRD","patients":3,"qty":120.0,"mrns":["16172","30145","125011"]},{"drug":"ROSUVASTATIN - IVARIN 20 MG F.C TABLET -TRD","patients":3,"qty":120.0,"mrns":["30145","158042","231019"]},{"drug":"ATORVASTATIN-ATORVA-20 MG TAB","patients":2,"qty":120.0,"mrns":["319222","554773"]},{"drug":"FINASTERIDE - FINISCAR 5 MG F.C. TABLET -TRD","patients":4,"qty":116.0,"mrns":["142065","639593","591832","680671"]},{"drug":"SOMATROPIN - OMNITROPE  5MG/1.5ML CARTRIDGE -TRD","patients":6,"qty":114.0,"mrns":["575045","500990","494939","490504","692044","720881"]},{"drug":"ASPIRIN -BAYER 100 MG F.C TABLET -TRD","patients":4,"qty":110.0,"mrns":["141360","16172","158042","231019"]},{"drug":"BLOOD GLUCOSE TEST STRIPS","patients":1,"qty":100.0,"mrns":["16172"]},{"drug":"MULTIVITAMINS ADULT- AR VITA TABLET -TRD","patients":3,"qty":90.0,"mrns":["335603","515558","803945"]},{"drug":"FUROSEMIDE - DIUSEMIDE 40 MG TABLET -TRD","patients":2,"qty":90.0,"mrns":["283310","319222"]},{"drug":"LEVOTHYROXINE - ELTROXIN 50 MCG TABLET -TRD","patients":2,"qty":90.0,"mrns":["30145","203029"]},{"drug":"ASPIRIN, ASA-BAYER ASPIRIN 100 MG TABLET","patients":3,"qty":79.0,"mrns":["650030","203840","658264"]},{"drug":"bisOPROLOL-CARDICOR 5 MG F.C. TABLET -TRD","patients":3,"qty":75.0,"mrns":["141360","186307","158042"]},{"drug":"ALLOPURINOL - NO-URIC 100 MG TABLET  -TRD","patients":2,"qty":60.0,"mrns":["670154","249268"]},{"drug":"EZETIMIBE - ZETEX 10 MG TABLET  -TRD","patients":2,"qty":60.0,"mrns":["237991","231019"]},{"drug":"FOLIC ACID-BEFOLVIT-1 MG TABLET","patients":2,"qty":60.0,"mrns":["251327","274540"]},{"drug":"MIRABEGRON - BETMIGA 50 MG F.C. TABLET -TRD","patients":2,"qty":60.0,"mrns":["151835","184908"]},{"drug":"SpironoLACtone  -NORACTONE-25 MG TABLET","patients":2,"qty":60.0,"mrns":["658264","319222"]},{"drug":"prednisoLONE - GUPISONE 5 MG TABLET -TRD","patients":2,"qty":60.0,"mrns":["385923","203029"]},{"drug":"APIXABAN - XCARD 5 MG F.C TABLET -TRD","patients":1,"qty":60.0,"mrns":["186307"]},{"drug":"HYDROXYUREA - CUREAML 500 MG CAPSULE -TRD","patients":1,"qty":60.0,"mrns":["101729"]},{"drug":"PROPRANOLOL - INDICARDIN 40 MG TABLET -TRD","patients":1,"qty":60.0,"mrns":["511133"]},{"drug":"TICAGRELOR - TICAGRELOR SPC 90 MG F.C. TABLET -TRD","patients":1,"qty":60.0,"mrns":["237991"]},{"drug":"VALPROIC ACID - DEPAKINE CHRONO 500 MG TABLET -TRD","patients":1,"qty":60.0,"mrns":["194066"]},{"drug":"VITAMIN B COMPLEX - NEUROVIT 250 MCG,100MG ,250 MG TABLET BOX30 -TRD","patients":1,"qty":60.0,"mrns":["193159"]},{"drug":"lamoTRIgine - LOXOL 100 MG TABLET -TRD","patients":1,"qty":60.0,"mrns":["234060"]},{"drug":"levETIRAcetam - EPITAM 500 MG F.C TABLET -TRD","patients":1,"qty":60.0,"mrns":["406964"]},{"drug":"metFORMIN - GLUCARE 500 MG F.C. TABLET -TRD","patients":1,"qty":60.0,"mrns":["319222"]},{"drug":"metFORMIN - GLUCOPHAGE 500 MG F.C TABLET -TRD","patients":1,"qty":60.0,"mrns":["125011"]},{"drug":"METHOTREXATE - EBEWE PHARMA 2.5 MG TABLET -TRD","patients":2,"qty":56.0,"mrns":["35665","274540"]},{"drug":"OMEPRAZOLE - LOSEC MUPS 10 MG TABLET -TRD","patients":1,"qty":56.0,"mrns":["318847"]},{"drug":"TELMISARTAN - NIZORTAN 80 MG TABLET -TRD","patients":1,"qty":56.0,"mrns":["30145"]},{"drug":"SIMETHICONE - AERO-OM 42 MG CHEWABLE TABLET -TRD","patients":2,"qty":50.0,"mrns":["678976","252872"]},{"drug":"POLYETHYLENE GLYCOL -  MOVICOL POWDER SACHET -TRD","patients":1,"qty":40.0,"mrns":["623089"]},{"drug":"SOLIFENACIN - SOLFISAN 10 MG F.C TABLET -TRD","patients":2,"qty":35.0,"mrns":["446837","275896"]},{"drug":"AMITRIPTYLINE- ALATRIPT 10 MG TABLET  -TRD","patients":1,"qty":30.0,"mrns":["188176"]},{"drug":"ATORVASTATIN-ATORVA-40 MG TAB","patients":1,"qty":30.0,"mrns":["650030"]},{"drug":"CARVEDILOL- CARVIDOL 25 MG TABLET -TRD","patients":1,"qty":30.0,"mrns":["150735"]},{"drug":"CETIRIZINE - CETRALON 10 MG F.C. TABLET -TRD","patients":1,"qty":30.0,"mrns":["836482"]},{"drug":"CLOPIDOGREL-CLOGREL 75 MG TABLET -TRD","patients":1,"qty":30.0,"mrns":["836482"]},{"drug":"DIENOGEST - VISANNE  2 MG TABLET -TRD","patients":1,"qty":30.0,"mrns":["552729"]},{"drug":"EMPAGLIFLOZIN-SPC-10 MG F.C TABLET -TRD","patients":1,"qty":30.0,"mrns":["186307"]},{"drug":"ENTECAVIR - ELIVE  0.5 MG F.C TABLET -TRD","patients":1,"qty":30.0,"mrns":["129885"]},{"drug":"ISOSORBIDE DINITRATE - ISOREM 5 MG SUBLINGUAL TABLET -TRD","patients":1,"qty":30.0,"mrns":["141360"]},{"drug":"LEVOTHYROXINE - ELTROXIN 100 MCG TABLET -TRD","patients":1,"qty":30.0,"mrns":["16172"]},{"drug":"LINAGLIPTIN - LIPTYN 5 MG F.C TABLET -TRD","patients":1,"qty":30.0,"mrns":["42263"]},{"drug":"MAGNESIUM OXIDE  - MAGLIVARA 400 MG TABLET -TRD","patients":1,"qty":30.0,"mrns":["564274"]},{"drug":"MESALAZINE - PENTASA 1000 MG SUPPOSITORY -TRD","patients":1,"qty":30.0,"mrns":["790604"]},{"drug":"SOLIFENACIN - SOLFISAN 5 MG F.C TABLET -TRD","patients":1,"qty":30.0,"mrns":["680671"]},{"drug":"TADALAFIL - AVIALIS 5 MG F.C. TABLET -TRD","patients":1,"qty":30.0,"mrns":["680671"]},{"drug":"TELMISARTAN - NIZORTAN 40 MG TABLET -TRD","patients":1,"qty":30.0,"mrns":["450224"]},{"drug":"THEOPHYLLINE -NUELIN 300 MG SR TABLET -TRD","patients":1,"qty":30.0,"mrns":["49117"]},{"drug":"MONTELUKAST-LEUKAIR 10 MG F.C. TABLET -TRD","patients":1,"qty":28.0,"mrns":["515558"]},{"drug":"MONTELUKAST-REOVAIR-5 MG TAB (CHEW)","patients":1,"qty":28.0,"mrns":["591673"]},{"drug":"POLYETHYLENE GLYCOL; PROPYLENE GLYCOL - SYSTANE- 0.4% /0.3% EYE DROPS -TRD","patients":15,"qty":24.0,"mrns":["57235","350970","311874","132813","335603","704331","268562","67748","15604","536372","752884","245027","41889","67635","779946"]},{"drug":"SALBUTAMOL - BUTALIN  100 MCG INHALER -TRD","patients":13,"qty":20.0,"mrns":["209871","49117","146840","35665","25715","151393","675924","664518","837428","515558","572209","647443","623089"]},{"drug":"INSULIN ASPART - novoRAPID100 UNIT/ML IN 3ML FLEXPEN -TRD","patients":4,"qty":18.0,"mrns":["299031","335603","60771","564124"]},{"drug":"CHOLECALCIFEROL; VITAMIN D3- D-SEUL 10,000 UNIT CAPSULE -TRD","patients":4,"qty":17.0,"mrns":["320489","25715","274540","385923"]},{"drug":"CARBIMAZOLE - MACLEODS  5 MG TABLET -TRD","patients":1,"qty":15.0,"mrns":["320489"]},{"drug":"INSULIN GLARGINE - LANTUS SOLOSTAR 300 UNIT/3ML PEE-FILLED PEN -TRD","patients":5,"qty":14.0,"mrns":["335603","16172","60771","593530","564124"]},{"drug":"BIMATOPROST - LUMIGAN 0.1MG/ML EYE DROPS -TRD","patients":11,"qty":13.0,"mrns":["415215","118065","412375","228092","464146","753097","85878","58172","105092","365412","66438"]},{"drug":"brinZOLamide:TIMOLOL-AZARGA-EYE DROPS 5 MG/ML","patients":6,"qty":12.0,"mrns":["118065","275599","753097","704331","105092","67635"]},{"drug":"CARBOMER (POLYACRYLIC ACID) - ARTELAC NIGHT TIME 0.2 % EYE GEL -TRD","patients":9,"qty":11.0,"mrns":["118065","412375","791350","826824","425422","384780","208586","704331","41889"]},{"drug":"FOLIC ACID - FOLICUM 5 MG TABLET -TRD","patients":2,"qty":8.0,"mrns":["188176","389574"]},{"drug":"TIOTROPIUM - SPIRIVA 18MCG (HARD CAPSULE) INHALER -TRD","patients":6,"qty":7.0,"mrns":["209871","283310","151393","14387","515558","60553"]},{"drug":"DICLOFENAC - AVOTRENE 1% IN 100 G TUBE -TRD","patients":5,"qty":7.0,"mrns":["472667","256359","569108","489466","274540"]},{"drug":"MOMETASONE FUROATE-AVOCOM 0.05 % NASAL SPRAY -TRD","patients":5,"qty":7.0,"mrns":["362040","601351","692267","450199","842486"]},{"drug":"BUDESONIDE;FORMOTEROL - BUFOMIX 160 MCG; 4.5 MCG/DOSE INHALER -TRD","patients":5,"qty":6.0,"mrns":["320400","362040","601351","515558","671836"]},{"drug":"SALBUTAMOL - BRONCHOVENT 5 MG/ML BOTTLE NEBULIZER -TRD","patients":2,"qty":5.0,"mrns":["450224","623089"]},{"drug":"FLUTICASONE-FLUSORT 0.05 % NASAL SPRAY -TRD","patients":4,"qty":4.0,"mrns":["778320","797673","132754","433707"]},{"drug":"DORZOLAMIDE; TIMOLOL - XOLAMOL 2%; 0.5% EYE DROPS, 5 ML -TRD","patients":1,"qty":4.0,"mrns":["19524"]},{"drug":"ETANERCEPT - NEPEXTO 50 MG PRE-FILLED PEN -TRD","patients":1,"qty":4.0,"mrns":["385923"]},{"drug":"BRIMONIDINE TARTRATE; TIMOLOL -  BRIMOCOM 2 MG/ML ; 5MG/ML EYE DROPS -TRD","patients":2,"qty":3.0,"mrns":["132813","390653"]},{"drug":"INSULIN GLARGINE -TOUJEO 300 UNIT/ML PRE-FILLED PEN, 1.5 ML  -TRD","patients":1,"qty":3.0,"mrns":["299031"]},{"drug":"DORZOLAMIDE-XOLA 2% EYE DROPS -TRD","patients":2,"qty":2.0,"mrns":["119903","390653"]},{"drug":"BRIMONIDINE TARTRATE - BRIMO-P 0.15% EYE DROPS -TRD","patients":1,"qty":2.0,"mrns":["268562"]},{"drug":"TIMOLOL - OPTIMOL 0.5% EYE DROP -TRD","patients":1,"qty":2.0,"mrns":["268562"]},{"drug":"TRAVOPROST;TIMOLOL - DUOTRAV 0.004%;0.5% EYE DROPS -TRD","patients":1,"qty":2.0,"mrns":["145797"]},{"drug":"VALPROIC ACID - DEPAKINE 57.64 MG/ML IN 150 ML SYRUP -TRD","patients":1,"qty":2.0,"mrns":["251327"]},{"drug":"BACLOFEN - CRESCENT 5MG/5ML IN 300 ML SYRUP -TRD","patients":1,"qty":1.0,"mrns":["546805"]},{"drug":"CHOLECALCIFEROL; VITAMIN D3 - TOPFEROL 50,000 UNIT TABLET -TRD","patients":1,"qty":1.0,"mrns":["677148"]},{"drug":"CHOLECALCIFEROL; VITAMIN D3- VIDROP 2800 UNIT/ML ORAL DROPS -TRD","patients":1,"qty":1.0,"mrns":["107151"]},{"drug":"DENOSUMAB - PROLIA 60MG/ 1ML  PRE-FILLED SYRINGE -TRD","patients":1,"qty":1.0,"mrns":["677148"]},{"drug":"FLUTICASONE FURATE, VILANTEROL - RELVAR ELLIPTA 200 MCG/ 25 MCG INHALER -TRD","patients":1,"qty":1.0,"mrns":["25715"]},{"drug":"FLUTICASONE PROPIONATE - FLIXOTIDE EVOHALER 50 MCG INHALER -TRD","patients":1,"qty":1.0,"mrns":["647443"]},{"drug":"FLUTICASONE PROPIONATE- FLIXOTIDE - 125 MCG INHALER -TRD","patients":1,"qty":1.0,"mrns":["664518"]}]}